{
  "metadata": {
    "title": "설 연휴에 읽기 좋은 장기작 웹툰 3선",
    "url": "https://zdnet.co.kr/view/?no=20250124182210",
    "date": "입력 :2025/01/27 09:32    수정: 2025/01/27 17:58",
    "author": "조수민 기자",
    "category": "인터넷",
    "source": "zdnet",
    "created_at": "2025-05-08T05:03:44.528738"
  },
  "content": {
    "text": "설 연휴에 읽기 좋은 장기작 웹툰 3선\n이달 27일이 임시공휴일로 지정되며 설 연휴가 6일로 늘어났다. 소비자들이 웹툰을 즐길 만한 여유가 확대된 가운데, 네이버웹툰·카카오엔터·리디가 추천한 '설 연휴에 읽기 좋은 장기작'을 소개한다.\n메디컬 드라마 웹툰 '중증외상센터: 골든 아워'\n네이버웹툰의 추천작은 '홍비치라' 작가의 '중증외상센터: 골든 아워'다. 동명의 웹소설을 원작으로 한다. 2019년 12월 네이버웹툰에서 연재를 시작해 2022년에 완결됐다. 총 149화다.\n이 작품은 사명감이 돋보이는 외과 의사 '백강혁'을 주인공으로 한 메디컬 드라마 웹툰이다. 대학 병원의 중증외상센터장이자 초임 교수인 백강혁을 중심으로 중증외상팀의 구성과 그들이 직면하는 이야기를 다룬다. 병원 내에서 벌어지는 의료 사건들을 사실적으로 묘사하며, 탄탄한 고증과 현실적인 전개가 펼쳐진다.\n네이버웹툰 관계자는 \"21일부터 백강혁 의사의 신입 시절을 프리퀄 외전 '중증외상센터: 외과의사 백강혁'이 공개될 예정\"이라며 \"24일 넷플릭스 시리즈로 공개되어 글로벌 시청자들을 찾아간다\"고 설명했다.\n반려 동물 소재의 웹툰 '무지개다리 파수꾼'\n카카오엔터의 추천작은 '이서' 작가의 '무지개다리 파수꾼'이다. 누적 조회 수 약 5천100만회를 기록했다. 2020년 9월 28일부터 카카오웹툰에서 연재 중이다. 현재까지 총 161화 공개됐다.\n이 작품은 반려 동물을 소재로 한 웹툰이다. 등장하는 귀여운 동물들의 면면이 눈을 사로잡는 한편 동물권에 대한 깊은 고민과 이야기들을 탄탄한 에피소드로 풀어냈다. 돈과 성공 만을 좇던 유명 수의사 '한철'은 사고를 계기로 동물들의 속마음을 들을 수 있게 되고, 번식장에 있던 웰시코기 '밍구'를 만나게 되면서 커다란 삶의 전환점을 맞이하게 된다. '한철'을 비롯해 수의 테크니션 '나영', 기자 '동욱' 등 등장인물과 유기견 출신의 '몽이'를 비롯한 다양한 동물 이야기들이 펼쳐진다.\n카카오엔터 관계자는 \"귀여운 동물들의 작화가 인상적이고, 동물들의 심리도 세심하게 묘사되어 있어 독자들에게 색다른 재미를 선사하는 작품\"이라며 \"반려동물 문화가 정착됐음에도 아직 많이 논의되지 않는 동물권과 관련된 의식들을 세심하게 다루고 윤리적인 문제에 부딪친 등장인물들의 고민들이 작품의 깊이감을 더해준다\"고 말했다.\n서스펜스 로맨스물 '탄금'\n리디의 추천작은 '장다혜' 작가의 '탄금'이다. 동명의 소설을 원작으로 한다. 2023년 11월부터 리디에서 연재 중이다. 현재까지 총 58화 공개됐다.\n이 작품은 서스펜스 로맨스물이다. 조선 최고 상단인 민상단의 배다른 오누이 '홍랑'과 '재이'가 주인공이다. 홍랑이 실종되자, 재이는 동생을 찾기 위해 노력한다. 그런 '재이'를 지켜보는 양오라버니 '무진'은 씁쓸함을 느낀다. 그러던 중, 자신이 사라진 '홍랑'이라 주장하는 낯선 남자가 '재이' 앞에 나타난다. 동생이 아니라고 부인하면서도 '재이'는 그에게 흔들리고 '무진'은 '재이' 근처를 맴돈다. 그리고 '홍랑'은 홀연히 돌아온다. 이 세 남녀의 이야기가 펼쳐진다.\n리디 관계자는 \"주인공 재이를 중심으로 펼쳐지는 세 주인공의 삼각관계와 섬세한 감정변화가 눈길을 사로잡는 작품\"이라며 \"애절한 삼각관계와 함께 10년만에 돌아온 홍랑의 정체도 작품의 흥미 요소\"라고 밝혔다.",
    "embeddings": [
      {
        "text": "설 연휴에 읽기 좋은 장기작 웹툰 3선\n이달 27일이 임시공휴일로 지정되며 설 연휴가 6일로 늘어났다 소비자들이 웹툰을 즐길 만한 여유가 확대된 가운데, 네이버웹툰·카카오엔터·리디가 추천한 '설 연휴에 읽기 좋은 장기작'을 소개한다 메디컬 드라마 웹툰 '중증외상센터: 골든 아워'\n네이버웹툰의 추천작은 '홍비치라' 작가의 '중증외상센터: 골든 아워'다 동명의 웹소설을 원작으로 한다 2019년 12월 네이버웹툰에서 연재를 시작해 2022년에 완결됐다 총 149화다 이 작품은 사명감이 돋보이는 외과 의사 '백강혁'을 주인공으로 한 메디컬 드라마 웹툰이다 대학 병원의 중증외상센터장이자 초임 교수인 백강혁을 중심으로 중증외상팀의 구성과 그들이 직면하는 이야기를 다룬다 병원 내에서 벌어지는 의료 사건들을 사실적으로 묘사하며, 탄탄한 고증과 현실적인 전개가 펼쳐진다 네이버웹툰 관계자는 \"21일부터 백강혁 의사의 신입 시절을 프리퀄 외전 '중증외상센터: 외과의사 백강혁'이 공개될 예정\"이라며 \"24일 넷플릭스 시리즈로 공개되어 글로벌 시청자들을 찾아간다\"고 설명했다 반려 동물 소재의 웹툰 '무지개다리 파수꾼'\n카카오엔터의 추천작은 '이서' 작가의 '무지개다리 파수꾼'이다 누적 조회 수 약 5천100만회를 기록했다 2020년 9월 28일부터 카카오웹툰에서 연재 중이다 현재까지 총 161화 공개됐다 이 작품은 반려 동물을 소재로 한 웹툰이다 등장하는 귀여운 동물들의 면면이 눈을 사로잡는 한편 동물권에 대한 깊은 고민과 이야기들을 탄탄한 에피소드로 풀어냈다 돈과 성공 만을 좇던 유명 수의사 '한철'은 사고를 계기로 동물들의 속마음을 들을 수 있게 되고, 번식장에 있던 웰시코기 '밍구'를 만나게 되면서 커다란 삶의 전환점을 맞이하게 된다 '한철'을 비롯해 수의 테크니션 '나영', 기자 '동욱' 등 등장인물과 유기견 출신의 '몽이'를 비롯한 다양한 동물 이야기들이 펼쳐진다 카카오엔터 관계자는 \"귀여운 동물들의 작화가 인상적이고, 동물들의 심리도 세심하게 묘사되어 있어 독자들에게 색다른 재미를 선사하는 작품\"이라며 \"반려동물 문화가 정착됐음에도 아직 많이 논의되지 않는 동물권과 관련된 의식들을 세심하게 다루고 윤리적인 문제에 부딪친 등장인물들의 고민들이 작품의 깊이감을 더해준다\"고 말했다 서스펜스 로맨스물 '탄금'\n리디의 추천작은 '장다혜' 작가의 '탄금'이다 동명의 소설을 원작으로 한다 2023년 11월부터 리디에서 연재 중이다 현재까지 총 58화 공개됐다 이 작품은 서스펜스 로맨스물이다 조선 최고 상단인 민상단의 배다른 오누이 '홍랑'과 '재이'가 주인공이다 홍랑이 실종되자, 재이는 동생을 찾기 위해 노력한다 그런 '재이'를 지켜보는 양오라버니 '무진'은 씁쓸함을 느낀다 그러던 중, 자신이 사라진 '홍랑'이라 주장하는 낯선 남자가 '재이' 앞에 나타난다 동생이 아니라고 부인하면서도 '재이'는 그에게 흔들리고 '무진'은 '재이' 근처를 맴돈다 그리고 '홍랑'은 홀연히 돌아온다 이 세 남녀의 이야기가 펼쳐진다 리디 관계자는 \"주인공 재이를 중심으로 펼쳐지는 세 주인공의 삼각관계와 섬세한 감정변화가 눈길을 사로잡는 작품\"이라며 \"애절한 삼각관계와 함께 10년만에 돌아온 홍랑의 정체도 작품의 흥미 요소\"라고 밝혔다.",
        "embedding": [
          -0.0033744690008461475,
          -0.01111162081360817,
          0.01747717149555683,
          -0.012757541611790657,
          -0.015097525902092457,
          -0.0012509662192314863,
          -0.03154351934790611,
          -0.018058862537145615,
          -0.0318872444331646,
          -0.004395733121782541,
          0.001092323218472302,
          0.026136435568332672,
          -0.02658592350780964,
          -0.013392114080488682,
          -0.010543149895966053,
          0.01444973424077034,
          0.02136392518877983,
          0.00589623162522912,
          0.010172982700169086,
          -0.03424045071005821,
          0.01644599251449108,
          -0.013669739477336407,
          -0.01827038638293743,
          0.0044783600606024265,
          0.019037161022424698,
          0.018072081729769707,
          0.0034835359547287226,
          -0.01811174303293228,
          0.009108752943575382,
          0.01111162081360817,
          0.00724469730630517,
          -0.00744300102815032,
          -0.006190382409840822,
          -0.014119227416813374,
          -0.0026721430476754904,
          0.01548091322183609,
          0.0041842092759907246,
          -0.020345965400338173,
          0.013682959601283073,
          -0.014542276039719582,
          0.003764466382563114,
          -0.005443438421934843,
          0.0013914314331486821,
          -0.011918055824935436,
          -0.02008156105875969,
          0.027339478954672813,
          0.016155146062374115,
          -0.03804787993431091,
          -0.0031877330038696527,
          0.019975798204541206,
          -0.0010807554936036468,
          0.0069736819714307785,
          -0.011230602860450745,
          -0.009439258836209774,
          -0.0036818399094045162,
          0.004342852160334587,
          -0.0028357438277453184,
          0.0035628576297312975,
          0.009459089487791061,
          -0.03127911314368248,
          0.008289096876978874,
          -0.0033695113379508257,
          -0.026480162516236305,
          0.015494133345782757,
          0.011376026086509228,
          -0.0030307425186038017,
          -0.015057865530252457,
          -0.023941874504089355,
          -0.0160229429602623,
          -0.0009543368360027671,
          0.018058862537145615,
          0.03693738207221031,
          0.006580379791557789,
          -0.014806680381298065,
          0.03392316401004791,
          -0.02977200411260128,
          -0.009293836541473866,
          0.0031067589297890663,
          0.0034306549932807684,
          0.0014195244293659925,
          0.029507599771022797,
          -0.026889989152550697,
          -0.01984359696507454,
          0.03273333981633186,
          0.003078665817156434,
          -0.007535542827099562,
          -0.028952348977327347,
          0.01914292201399803,
          0.006781988777220249,
          -0.003648789133876562,
          0.010020949877798557,
          -0.0068877507001161575,
          0.009155023843050003,
          0.00925417523831129,
          -0.005264964886009693,
          0.012268392369151115,
          -0.020134441554546356,
          0.023849332705140114,
          -0.023241201415657997,
          -0.01825716532766819,
          -0.00846096035093069,
          -0.012526187114417553,
          -0.0058631813153624535,
          0.0033529859501868486,
          -0.04476376995444298,
          0.00010648498573573306,
          0.019116481766104698,
          -0.022725610062479973,
          0.03328859061002731,
          -0.003124936716631055,
          0.003972685430198908,
          0.014396852813661098,
          -0.01643277145922184,
          -0.037519071251153946,
          -0.011230602860450745,
          -0.004590732045471668,
          -0.0007019126787781715,
          -0.007522322703152895,
          -0.00704639358446002,
          -0.012050257995724678,
          0.005810300353914499,
          0.041405823081731796,
          0.013828381896018982,
          -0.023056117817759514,
          0.01816462352871895,
          0.01056298054754734,
          -0.025700166821479797,
          -0.03503366559743881,
          0.0011856912169605494,
          -0.020583929494023323,
          0.05034271255135536,
          0.006593599915504456,
          0.04087701439857483,
          0.014767020009458065,
          -0.02095409668982029,
          0.019090041518211365,
          -0.01676327735185623,
          -0.007535542827099562,
          -0.009240955114364624,
          -0.034108247607946396,
          0.027286596596240997,
          -0.004237090237438679,
          -0.011065349914133549,
          -0.036805178970098495,
          0.022990016266703606,
          0.008983160369098186,
          0.0355360321700573,
          0.010014340281486511,
          -0.0009964763885363936,
          0.00352319679223001,
          -0.0025845589116215706,
          0.011607379652559757,
          0.010615861043334007,
          -0.0008299838518723845,
          0.030750302597880363,
          -0.00488488283008337,
          0.00781977828592062,
          0.014568716287612915,
          -0.026215756312012672,
          -0.003853703150525689,
          0.020055120810866356,
          0.004124718252569437,
          0.0021449855994433165,
          -0.00742317084223032,
          -0.005625216756016016,
          0.035694677382707596,
          0.0007791685056872666,
          -0.0017913439078256488,
          -0.00801147148013115,
          -0.011640430428087711,
          -0.019751055166125298,
          0.016644295305013657,
          -0.006993512623012066,
          -0.017437510192394257,
          -0.029005229473114014,
          0.01928834617137909,
          -0.0008832779712975025,
          0.009194684214890003,
          -0.02897878922522068,
          -0.00960451178252697,
          -0.0061804670840501785,
          -0.00996806938201189,
          0.010186202824115753,
          0.018005982041358948,
          -0.0320458859205246,
          0.007350459229201078,
          -0.015864301472902298,
          -0.0015525531489402056,
          -0.005040220450609922,
          -0.0023284165654331446,
          0.027524562552571297,
          0.02580592967569828,
          0.017397848889231682,
          -0.01819106563925743,
          -0.607496976852417,
          0.012909574434161186,
          0.0030125644989311695,
          0.013392114080488682,
          0.01191144622862339,
          -0.009617731906473637,
          0.00801808200776577,
          0.01563955657184124,
          -0.017609374597668648,
          -0.0003257552452851087,
          0.022818151861429214,
          0.007403340190649033,
          0.018072081729769707,
          -0.012532797642052174,
          -0.00569792790338397,
          -0.02214391902089119,
          -0.01755649223923683,
          -0.022990016266703606,
          -0.00762147456407547,
          0.006355635356158018,
          -0.02715439535677433,
          0.014833121560513973,
          -0.012836863286793232,
          -0.008275876753032207,
          0.016155146062374115,
          0.042674969881772995,
          -4.314655961934477e-05,
          -0.006154026836156845,
          -0.0006279618828557432,
          0.04746070131659508,
          -0.03201944753527641,
          0.03773059695959091,
          0.018481910228729248,
          0.002958031138405204,
          0.06033722311258316,
          -0.021707652136683464,
          -0.013550756499171257,
          0.031226232647895813,
          0.025462202727794647,
          0.04174955189228058,
          -0.01274432148784399,
          -0.008031302131712437,
          0.020359186455607414,
          -0.00857333280146122,
          -0.011071959510445595,
          0.01130992453545332,
          -0.0014748842222616076,
          -0.013868043199181557,
          0.00413132831454277,
          -0.013319402933120728,
          -0.01841580867767334,
          -0.013973805122077465,
          0.019817154854536057,
          0.007740456610918045,
          -0.0025796014815568924,
          0.03305062651634216,
          0.028317777439951897,
          -0.009776375256478786,
          -0.004022261127829552,
          0.012724490836262703,
          0.008077573031187057,
          0.016710396856069565,
          -0.019989019259810448,
          -0.020861554890871048,
          -0.029243193566799164,
          0.037043143063783646,
          -0.004822086542844772,
          -0.004402343649417162,
          -0.026453722268342972,
          -0.013081437908113003,
          -0.0018789281602948904,
          -0.013577197678387165,
          -0.018931398168206215,
          -0.009716884233057499,
          0.012440255843102932,
          0.01737140864133835,
          0.03294486552476883,
          0.00509971147403121,
          -0.00881790742278099,
          0.03527162969112396,
          0.0021714260801672935,
          0.006454787217080593,
          0.007218257058411837,
          0.01873309537768364,
          -0.008731975220143795,
          -0.0049575939774513245,
          -0.025528304278850555,
          -0.0037016700953245163,
          0.0063754660077393055,
          -0.014965323731303215,
          -0.003476925892755389,
          0.008189945481717587,
          -0.0005407909047789872,
          0.020755793899297714,
          -0.0002441614924464375,
          0.02310899831354618,
          -0.0074826618656516075,
          0.01452905498445034,
          -0.008474180474877357,
          -0.025924911722540855,
          0.0023350268602371216,
          -9.218026207236107e-06,
          0.006586989853531122,
          -0.022514086216688156,
          -0.00035901242517866194,
          0.007290968205779791,
          -0.03371163830161095,
          -0.04024244472384453,
          0.03352655470371246,
          -0.0019582496024668217,
          -0.003764466382563114,
          -0.0015385067090392113,
          -0.015586675144731998,
          -0.011323144659399986,
          -0.010463828220963478,
          -0.016723617911338806,
          0.01468769833445549,
          0.03421400859951973,
          0.0062763141468167305,
          0.0023383318912237883,
          0.024404583498835564,
          -0.02279171161353588,
          0.015375151298940182,
          0.0010394422570243478,
          0.004121412988752127,
          0.004289971198886633,
          0.01071501336991787,
          0.0011088484898209572,
          -0.010338235646486282,
          -0.02445746399462223,
          0.0015376803930848837,
          -0.012096528895199299,
          -0.0038999738171696663,
          -0.02222324162721634,
          0.012612119317054749,
          -0.009181464090943336,
          0.015335490927100182,
          -0.009307056665420532,
          0.021139180287718773,
          -0.03135843575000763,
          -0.01865377277135849,
          0.0035463322419673204,
          -0.0018904958851635456,
          -0.018918178975582123,
          -0.004240395501255989,
          -0.018058862537145615,
          -0.037836357951164246,
          -0.0025482033379375935,
          0.01095297746360302,
          -0.006395296193659306,
          -0.011342975310981274,
          0.01889173872768879,
          -0.022170361131429672,
          0.005529369693249464,
          -0.0036157385911792517,
          0.0070860544219613075,
          0.009664002805948257,
          -0.01730530895292759,
          -0.03564179688692093,
          -0.014238209463655949,
          0.030300814658403397,
          0.016155146062374115,
          0.00015678390627726912,
          -0.00014500961697194725,
          -0.0018458775011822581,
          -0.024708649143576622,
          -0.0010757979471236467,
          -0.010377896949648857,
          -0.011871784925460815,
          -0.029163872823119164,
          -0.029983527958393097,
          0.012863303534686565,
          -0.029745563864707947,
          0.007595033850520849,
          0.014819900505244732,
          0.011825514025986195,
          -0.002582906512543559,
          0.001549248117953539,
          -0.01763581484556198,
          0.005959027912467718,
          -0.018204284831881523,
          0.01154788862913847,
          -0.019949357956647873,
          -0.028159134089946747,
          0.01448939461261034,
          0.0022623154800385237,
          -0.014198549091815948,
          0.010886876843869686,
          0.013630078174173832,
          0.0036719245836138725,
          0.0005250918329693377,
          0.01676327735185623,
          0.006454787217080593,
          0.0012526187347248197,
          0.0038008219562470913,
          -0.001471579191274941,
          0.01206347905099392,
          0.02874082513153553,
          0.027207275852560997,
          0.024312041699886322,
          0.026863548904657364,
          0.0052881003357470036,
          0.011647040955722332,
          -0.021006979048252106,
          0.00782638881355524,
          0.0020458337385207415,
          0.03357943519949913,
          -0.013868043199181557,
          0.011924666352570057,
          -0.0005304625374265015,
          0.005889621563255787,
          -0.03143775463104248,
          -0.0015880826395004988,
          0.008381638675928116,
          0.002910107607021928,
          0.02112596109509468,
          -0.02414017729461193,
          0.012122970074415207,
          -0.011468566954135895,
          0.014568716287612915,
          -0.0031133689917623997,
          0.0008783204248175025,
          -0.0013525969116017222,
          0.0030175221618264914,
          -0.016141926869750023,
          0.0005659919697791338,
          0.009194684214890003,
          -0.003704975126311183,
          -0.002283798297867179,
          -0.015163627453148365,
          -0.047037649899721146,
          -0.004574206657707691,
          -0.019632071256637573,
          0.03418756648898125,
          0.01353753637522459,
          -0.003467010799795389,
          0.01075467374175787,
          -0.020940877497196198,
          0.008983160369098186,
          0.005129457451403141,
          0.0009064134210348129,
          0.023122217506170273,
          -0.003751246025785804,
          -0.03350011631846428,
          0.007456221152096987,
          0.02731303684413433,
          0.026070334017276764,
          -0.0050567458383738995,
          -0.010483658872544765,
          0.03024793416261673,
          -0.03278622031211853,
          0.026321519166231155,
          0.004273445811122656,
          -0.002994386712089181,
          0.01000111922621727,
          -0.024034416303038597,
          0.014370412565767765,
          -0.009075702168047428,
          0.025673726573586464,
          0.024563224986195564,
          0.015256169252097607,
          0.0007118278881534934,
          -0.006167246960103512,
          0.007297578267753124,
          0.010060611180961132,
          0.006438261829316616,
          -0.0016343535389751196,
          -0.02723371610045433,
          -0.0032059107907116413,
          -0.015309049747884274,
          0.015837859362363815,
          -0.02008156105875969,
          -0.00547648873180151,
          -0.023280860856175423,
          -0.004471749998629093,
          -0.01425143051892519,
          0.01036467682570219,
          -0.011190942488610744,
          -0.005215388722717762,
          0.01819106563925743,
          -0.018442248925566673,
          -0.0328391008079052,
          -0.006765463389456272,
          0.007495881989598274,
          -0.00128071173094213,
          -0.029322516173124313,
          -0.024497125297784805,
          -0.004303191788494587,
          -0.004693189170211554,
          0.04849188029766083,
          -0.020345965400338173,
          0.01064230129122734,
          -0.006537414155900478,
          0.006025128997862339,
          -0.03484858199954033,
          -0.01452905498445034,
          0.02039884589612484,
          -0.002467229263857007,
          -0.003291842294856906,
          0.010549760423600674,
          0.011680091731250286,
          0.017754796892404556,
          -0.0004437046591192484,
          -0.03201944753527641,
          0.011124840937554836,
          0.0008692314731888473,
          -0.03540383279323578,
          -0.017596153542399406,
          0.022659510374069214,
          0.005030305590480566,
          -0.028079811483621597,
          -0.003267054446041584,
          -0.029560480266809464,
          -0.023373402655124664,
          -0.02929607592523098,
          0.008242825977504253,
          -0.003240613965317607,
          -0.020226983353495598,
          0.01578497886657715,
          -0.014661258086562157,
          0.00785943865776062,
          -0.0027993880212306976,
          -0.01619480736553669,
          -0.014542276039719582,
          0.08852279931306839,
          -0.008229605853557587,
          0.026731347665190697,
          0.006914190948009491,
          0.007535542827099562,
          0.007687575649470091,
          -0.00805774237960577,
          -0.041961073875427246,
          -0.0026787533424794674,
          -0.015494133345782757,
          0.018640553578734398,
          6.997437594691291e-05,
          0.03788923844695091,
          0.005066661164164543,
          0.0015228076372295618,
          0.008765025995671749,
          0.023915434256196022,
          -0.032654017210006714,
          0.023598147556185722,
          0.02158867008984089,
          0.013881263323128223,
          -0.008765025995671749,
          0.014145668596029282,
          0.010655522346496582,
          0.019737834110856056,
          -0.016062604263424873,
          -0.008487400598824024,
          0.022262902930378914,
          0.013411943800747395,
          -0.01628734916448593,
          -0.008037912659347057,
          -0.016168367117643356,
          -0.022514086216688156,
          0.003919804468750954,
          0.008778246119618416,
          0.03180792182683945,
          0.014555496163666248,
          0.029110992327332497,
          0.012843473814427853,
          0.012843473814427853,
          0.01969817280769348,
          0.043071575462818146,
          0.01684259995818138,
          0.011541279032826424,
          -0.008203165605664253,
          -0.008269267156720161,
          -0.00011402466043364257,
          0.035932641476392746,
          -0.008348587900400162,
          -0.01698802225291729,
          0.0355360321700573,
          0.011918055824935436,
          -0.023227980360388756,
          -0.0004899755585938692,
          0.030459458008408546,
          -0.018058862537145615,
          -0.020782234147191048,
          -0.008976549841463566,
          -0.01393414381891489,
          0.003470315830782056,
          0.021562227979302406,
          -0.03424045071005821,
          0.008004861883819103,
          0.007793337572365999,
          -0.024880511686205864,
          -0.01218907069414854,
          -0.003857008181512356,
          0.0007857786258682609,
          0.009472309611737728,
          -0.0034934512805193663,
          -0.022421544417738914,
          -0.015031425282359123,
          -0.01890495792031288,
          0.00028361569275148213,
          0.013154149055480957,
          -0.004422173835337162,
          0.04373258724808693,
          0.006322585046291351,
          0.001123721245676279,
          0.012625339441001415,
          -0.02358492650091648,
          -0.012076699174940586,
          0.003675229614600539,
          -0.021800193935632706,
          -0.019116481766104698,
          0.01409278716892004,
          0.00837502907961607,
          -0.014357192441821098,
          -0.009644173085689545,
          0.015705658122897148,
          0.01468769833445549,
          0.017014462500810623,
          0.005142677575349808,
          -0.02650660276412964,
          0.00881129689514637,
          -0.007079444359987974,
          0.03558891639113426,
          -0.006018518935889006,
          -0.0020904522389173508,
          -0.003794211894273758,
          0.0031133689917623997,
          -0.022117478772997856,
          -0.01866699382662773,
          0.010106881149113178,
          0.008976549841463566,
          0.0044651394709944725,
          0.0020921046379953623,
          0.027894727885723114,
          -0.009174853563308716,
          0.007436390966176987,
          0.009194684214890003,
          -0.015401591546833515,
          0.0015038035344332457,
          0.01946020871400833,
          4.128746149945073e-05,
          0.023558486253023148,
          -0.01289635431021452,
          0.0019020636100322008,
          0.008606383576989174,
          -0.02374356985092163,
          -0.009485529735684395,
          -0.03794211894273758,
          0.026096774265170097,
          0.01405312679708004,
          -0.012724490836262703,
          0.006332499906420708,
          -0.02492017298936844,
          -0.02358492650091648,
          0.01393414381891489,
          -0.007251307368278503,
          0.009029431268572807,
          0.029983527958393097,
          -0.00028836671845056117,
          -0.012612119317054749,
          -0.010734843090176582,
          -0.02690321020781994,
          -0.019565971568226814,
          0.00041086060809902847,
          0.006967071909457445,
          -0.02230256237089634,
          -0.025052374228835106,
          -0.04098277539014816,
          0.00035777303855866194,
          -0.020583929494023323,
          0.007945370860397816,
          -0.023598147556185722,
          -0.010100271552801132,
          -0.014991763979196548,
          -0.0082097752019763,
          -0.010172982700169086,
          -0.006438261829316616,
          -0.002273883204907179,
          0.0028720994014292955,
          0.023214759305119514,
          -0.002300323685631156,
          -0.02135070413351059,
          -0.010794335044920444,
          -0.010814164765179157,
          0.030195051804184914,
          0.020451728254556656,
          0.036249928176403046,
          -0.009518580511212349,
          0.012889744713902473,
          0.034028925001621246,
          0.016102265566587448,
          0.009419428184628487,
          -0.012539408169686794,
          0.0025448983069509268,
          -0.02437814138829708,
          0.032997746020555496,
          0.00413132831454277,
          0.029798444360494614,
          0.0022970186546444893,
          0.0070860544219613075,
          -0.015917181968688965,
          0.056952837854623795,
          -0.009029431268572807,
          0.0011509880423545837,
          0.0019764273893088102,
          -0.03130555525422096,
          -0.005787164904177189,
          0.0014947146410122514,
          -0.0019202413968741894,
          -0.01865377277135849,
          -0.009829256683588028,
          0.007092664483934641,
          -0.00042759248754009604,
          0.01611548475921154,
          0.014238209463655949,
          0.017530051991343498,
          0.013616858050227165,
          -0.029719123616814613,
          0.019909696653485298,
          0.005096406675875187,
          -0.014211769215762615,
          -0.004227174911648035,
          0.0038338727317750454,
          -0.027603883296251297,
          -0.0037148904521018267,
          0.011633820831775665,
          0.029163872823119164,
          -0.0004779946757480502,
          -0.004699799232184887,
          0.016102265566587448,
          0.007409950252622366,
          0.011389246210455894,
          -0.005707843229174614,
          -0.03127911314368248,
          0.004673358518630266,
          -0.009511969983577728,
          -0.025541523471474648,
          -0.016472432762384415,
          -0.011217382736504078,
          -0.019275125116109848,
          0.00294811581261456,
          -0.0035562473349273205,
          -0.011415686458349228,
          0.01787377893924713,
          -0.005066661164164543,
          0.007337239105254412,
          -0.004018956329673529,
          0.017001241445541382,
          0.04153802618384361,
          0.0011642082827165723,
          0.027683204039931297,
          0.03852381184697151,
          0.00940620806068182,
          -0.012929405085742474,
          0.005126152187585831,
          -0.006107755936682224,
          -0.005129457451403141,
          0.015375151298940182,
          0.02016088180243969,
          -0.006041654385626316,
          0.007310798391699791,
          0.014991763979196548,
          0.013167369179427624,
          -0.03630280867218971,
          -0.037043143063783646,
          0.01652531325817108,
          0.004891492892056704,
          0.021377144381403923,
          -0.02230256237089634,
          -0.011541279032826424,
          -0.0063622454181313515,
          0.03543027117848396,
          -0.015983283519744873,
          -0.011428906582295895,
          -0.02000223845243454,
          -0.004141243640333414,
          -0.015824640169739723,
          0.023452725261449814,
          -0.008824517019093037,
          0.017001241445541382,
          0.0022408324293792248,
          -0.021958835422992706,
          -0.009313666261732578,
          -0.02993064746260643,
          -0.023227980360388756,
          0.014039905741810799,
          -0.01667073555290699,
          0.03439909219741821,
          -0.006170551758259535,
          0.0020987146999686956,
          0.018442248925566673,
          -0.019552750512957573,
          0.008441129699349403,
          -0.025541523471474648,
          -0.03183436393737793,
          0.04669392481446266,
          0.008798076771199703,
          0.0001584364363225177,
          0.01597006246447563,
          -0.006980292499065399,
          -0.0006895186961628497,
          -0.010629081167280674,
          0.01373584009706974,
          0.024404583498835564,
          -0.020663252100348473,
          0.00762147456407547,
          0.014780240133404732,
          0.01345160510390997,
          -0.0003873120294883847,
          -0.009637562558054924,
          -0.015467693097889423,
          -0.003678534645587206,
          -0.03487502038478851,
          -0.006666311528533697,
          0.015758538618683815,
          0.04145870730280876,
          -0.010972808115184307,
          -0.0016029553953558207,
          -0.02174731157720089,
          0.04225192219018936,
          0.0006758852978236973,
          -0.023611366748809814,
          0.011567719280719757,
          0.018455469980835915,
          -0.017900219187140465,
          0.010437387973070145,
          0.007872658781707287,
          0.0025002798065543175,
          -0.0024705342948436737,
          -0.005033610388636589,
          0.009492140263319016,
          -0.014198549091815948,
          0.012671610340476036,
          -0.01635345071554184,
          -0.04042752459645271,
          -0.012043648399412632,
          0.0010600988753139973,
          -0.009776375256478786,
          -0.021324263885617256,
          0.0031381570734083652,
          0.005559115204960108,
          -0.01488600205630064,
          0.003764466382563114,
          -0.0019086736720055342,
          -0.02897878922522068,
          0.020742572844028473,
          0.005535979755222797,
          2.09632639780466e-06,
          0.028925908729434013,
          -0.022593408823013306,
          -0.004081752151250839,
          -0.02096731774508953,
          -0.0075619835406541824,
          0.009353327564895153,
          -0.01731852814555168,
          -0.005241829436272383,
          -0.004435393959283829,
          0.02421949990093708,
          -0.03852381184697151,
          -0.025382881984114647,
          -0.011964326724410057,
          -0.027762526646256447,
          -0.028687944635748863,
          0.017741575837135315,
          0.0007742109009996057,
          -0.014026685617864132,
          -0.01016637310385704,
          0.017569713294506073,
          0.004442004021257162,
          0.02065003104507923,
          0.016260908916592598,
          -0.008480791002511978,
          -0.007059613708406687,
          -0.036963820457458496,
          -0.03270690143108368,
          -0.006795208901166916,
          -0.025858810171484947,
          0.04732849821448326,
          -0.00865926407277584,
          -0.03294486552476883,
          -0.03662009537220001,
          0.0007097622146829963,
          -0.040136680006980896,
          0.006084620486944914,
          0.023386623710393906,
          0.017212767153978348,
          0.01310126855969429,
          -0.020531048998236656,
          0.01644599251449108,
          0.027577443048357964,
          -0.0037082803901284933,
          0.01170653197914362,
          0.007892489433288574,
          -0.023373402655124664,
          0.002404432976618409,
          -0.007839608937501907,
          0.011647040955722332,
          0.01770191639661789,
          -0.027260156348347664,
          5.45851762581151e-05,
          0.011699921451508999,
          0.032997746020555496,
          -0.002994386712089181,
          0.028793705627322197,
          -0.018310047686100006,
          -0.0024027805775403976,
          -0.00545665854588151,
          0.001232788315974176,
          -0.01993613876402378,
          -0.027498120442032814,
          0.02333374321460724,
          -0.014674478210508823,
          -0.010067220777273178,
          0.011038909666240215,
          0.0030456152744591236,
          -0.00861960370093584,
          0.01682937890291214,
          0.013947363942861557,
          0.012638559564948082,
          0.007403340190649033,
          0.005007170140743256,
          -0.010701793245971203,
          0.009141803719103336,
          -0.019486648961901665,
          0.006494448054581881,
          -0.0064580924808979034,
          0.0010567937279120088,
          0.009492140263319016,
          0.0066894469782710075,
          -0.019552750512957573,
          -0.0026903210673481226,
          0.0019218939123675227,
          -0.019275125116109848,
          -0.0005887142615392804,
          0.02128460258245468,
          0.004174293950200081,
          0.028317777439951897,
          -0.019975798204541206,
          0.013147539459168911,
          -0.009181464090943336,
          0.006686141714453697,
          -0.0036719245836138725,
          -0.022738831117749214,
          -0.03889397904276848,
          0.022011717781424522,
          0.026942871510982513,
          -0.00826265662908554,
          0.0033116727136075497,
          -0.008540282025933266,
          -0.008507231250405312,
          -0.0021862988360226154,
          -0.02238188497722149,
          -0.002462271600961685,
          -0.02770964615046978,
          -0.010979417711496353,
          0.008242825977504253,
          -0.007330629043281078,
          -0.006580379791557789,
          -0.02406085655093193,
          0.007006732746958733,
          -0.015811419114470482,
          0.02057071030139923,
          0.26546263694763184,
          -0.01953953132033348,
          0.00017888651927933097,
          0.032971303910017014,
          0.0035826878156512976,
          0.015665996819734573,
          0.02380967140197754,
          -0.0032422663643956184,
          -0.0007138935616239905,
          0.02166799083352089,
          -0.01652531325817108,
          -0.01119755208492279,
          -0.00837502907961607,
          -0.0028621843084692955,
          0.001923546427860856,
          -0.022447984665632248,
          -0.012023817747831345,
          -0.01056298054754734,
          -0.02127138338983059,
          -0.023003235459327698,
          0.00470640929415822,
          0.01873309537768364,
          -0.03508654609322548,
          -0.017292087897658348,
          0.008791466243565083,
          -0.004468444734811783,
          0.002667185617610812,
          -0.007271138019859791,
          0.008804687298834324,
          0.013398723676800728,
          -0.024113737046718597,
          -0.01035806629806757,
          -0.003638874040916562,
          -0.012526187114417553,
          -0.01842902973294258,
          -0.01690869964659214,
          0.027260156348347664,
          0.026493381708860397,
          0.021773753687739372,
          0.024166617542505264,
          -0.007965200580656528,
          0.018548011779785156,
          0.005945807788521051,
          -0.006821649149060249,
          0.01548091322183609,
          0.0061606368981301785,
          -0.004114802926778793,
          -0.005810300353914499,
          -0.030670981854200363,
          0.01191144622862339,
          -0.012360934168100357,
          -0.01865377277135849,
          0.04246344417333603,
          0.026493381708860397,
          0.01825716532766819,
          0.004960899241268635,
          0.007251307368278503,
          -0.01816462352871895,
          -0.027974050492048264,
          0.022752052173018456,
          0.00724469730630517,
          0.029957087710499763,
          -0.03373808041214943,
          0.028132693842053413,
          -0.015071085654199123,
          0.0028159134089946747,
          -0.016472432762384415,
          0.012783982791006565,
          -0.009664002805948257,
          -0.009036040864884853,
          -0.01004739012569189,
          -0.01930156536400318,
          -0.030856065452098846,
          -0.018217505887150764,
          -0.04571562632918358,
          -0.013002116233110428,
          0.05547217279672623,
          -0.004785730503499508,
          0.020504608750343323,
          0.031728602945804596,
          -0.004911323077976704,
          -0.00547648873180151,
          0.01587752066552639,
          0.006834869738668203,
          0.0026109993923455477,
          -0.02428559958934784,
          0.022976795211434364,
          0.018693434074521065,
          -0.02515813708305359,
          -0.005208778660744429,
          0.011435517109930515,
          -0.004293276462703943,
          -0.014608376659452915,
          -0.004967509303241968,
          0.007310798391699791,
          -0.008897229097783566,
          0.019354447722434998,
          0.0031431145034730434,
          -0.014833121560513973,
          0.010298575274646282,
          -0.0032852322328835726,
          0.009445869363844395,
          0.0004879098851233721,
          0.016631076112389565,
          -0.002759727416560054,
          0.0044783600606024265,
          -0.002534982981160283,
          -0.008355198428034782,
          0.0159436222165823,
          -0.012479916214942932,
          0.004666748456656933,
          -0.02287103421986103,
          0.014026685617864132,
          -0.005539285019040108,
          0.00706622377038002,
          0.028793705627322197,
          -0.0067753782495856285,
          -0.03476925939321518,
          -0.01930156536400318,
          -0.009756544604897499,
          -0.006686141714453697,
          -0.03572111576795578,
          -0.016102265566587448,
          -0.013643298298120499,
          -0.005294710397720337,
          -0.020055120810866356,
          -3.550360270310193e-05,
          0.01115789171308279,
          0.011918055824935436,
          -0.03685805946588516,
          0.00822299625724554,
          -0.01044399756938219,
          0.03495434299111366,
          -0.006246568635106087,
          0.00960451178252697,
          0.016776498407125473,
          0.012354324571788311,
          0.0021317654754966497,
          0.019711393862962723,
          0.0002780384093057364,
          0.0027746001724153757,
          -0.011832124553620815,
          -0.0051757278852164745,
          0.012195681221783161,
          -0.005602081306278706,
          -0.044023435562849045,
          0.02905810996890068,
          0.005311235785484314,
          0.0019433768466114998,
          0.004157769028097391,
          -0.010794335044920444,
          0.0021036723628640175,
          -0.0022028242237865925,
          -0.016234468668699265,
          0.003083623480051756,
          -0.022434765473008156,
          -0.05229931324720383,
          -0.02921675331890583,
          -0.011481788009405136,
          0.018852077424526215,
          -0.0326804593205452,
          0.011759412474930286,
          0.040691930800676346,
          -0.024655766785144806,
          -0.020517829805612564,
          -0.0007758634747005999,
          -0.16742125153541565,
          0.01329296175390482,
          0.041247181594371796,
          -0.005208778660744429,
          -0.006190382409840822,
          0.014211769215762615,
          0.038550250232219696,
          -0.0013658171519637108,
          -0.0034141296055167913,
          0.0009452479425817728,
          0.0067885988391935825,
          -0.01064230129122734,
          -0.022421544417738914,
          -0.00726452749222517,
          -0.0009047609055414796,
          0.03159639984369278,
          -0.03566823527216911,
          0.022685950621962547,
          0.027180835604667664,
          -0.004498190246522427,
          0.016802938655018806,
          -0.0009088922524824739,
          0.01803242228925228,
          0.009042651392519474,
          -0.003005954436957836,
          0.006114365998655558,
          -0.008434520103037357,
          -0.023307301104068756,
          0.0028754044324159622,
          -0.004233785439282656,
          -0.03149063512682915,
          -0.00027762525132857263,
          0.026466941460967064,
          -0.002796082990244031,
          0.01369617972522974,
          -0.004389123059809208,
          -0.02818557433784008,
          0.024259159341454506,
          -0.009293836541473866,
          0.03669941425323486,
          0.0037710764445364475,
          0.013213640078902245,
          0.02778896689414978,
          0.000768427038565278,
          -0.019711393862962723,
          0.014965323731303215,
          0.00490471301600337,
          0.015983283519744873,
          0.0013906051171943545,
          -0.012334493920207024,
          -0.01389448344707489,
          -0.021496128290891647,
          0.03350011631846428,
          -0.011898225173354149,
          -0.0017004547407850623,
          0.03336791321635246,
          0.0008725365623831749,
          -0.006342415232211351,
          0.005800385028123856,
          0.001353423111140728,
          -0.011270263232290745,
          -0.026969311758875847,
          0.023214759305119514,
          -0.0004437046591192484,
          -0.0019995628390461206,
          -0.0016806243220344186,
          -0.024113737046718597,
          -0.0024391361512243748,
          -0.02929607592523098,
          0.01349126547574997,
          -0.02366424910724163,
          0.016102265566587448,
          -0.006861309986561537,
          -0.03286554291844368,
          0.021456466987729073,
          -0.002179688774049282,
          -0.009637562558054924,
          0.014674478210508823,
          0.01249974686652422,
          0.022752052173018456,
          0.014343972317874432,
          0.00293820071965456,
          -0.02168121188879013,
          0.002263967879116535,
          -0.011455346830189228,
          0.023360183462500572,
          0.012783982791006565,
          -0.01595684327185154,
          0.00035529423621483147,
          0.016631076112389565,
          0.03318282961845398,
          -0.014793460257351398,
          0.011653650552034378,
          -0.019433768466114998,
          0.011124840937554836,
          0.01698802225291729,
          0.0038305677007883787,
          0.007700795773416758,
          0.010477048344910145,
          -0.009102142415940762,
          0.0018706654664129019,
          -0.010701793245971203,
          -0.017649034038186073,
          0.027048632502555847,
          0.006960461847484112,
          0.01119755208492279,
          0.01214941032230854,
          0.009260785765945911,
          0.04812171310186386,
          -0.0017169800121337175,
          -0.008884008042514324,
          0.004984034691005945,
          0.02612321451306343,
          0.024272380396723747,
          0.011052129790186882,
          0.041881754994392395,
          -0.006596905179321766,
          -0.0010435734875500202,
          0.04677324742078781,
          0.008077573031187057,
          0.05811621993780136,
          -0.026533043012022972,
          -0.05430879071354866,
          0.027762526646256447,
          -0.019499870017170906,
          -0.020055120810866356,
          -0.041564468294382095,
          -0.00609453534707427,
          0.016009723767638206,
          0.040533289313316345,
          -0.01906360127031803,
          0.04693188890814781,
          0.010351455770432949,
          -2.9984405500727007e-06,
          -0.023161878809332848,
          -0.012037037871778011,
          -0.018931398168206215,
          -0.011600770056247711,
          0.0066563962027430534,
          0.013973805122077465,
          0.01731852814555168,
          -0.008123843930661678,
          -0.0016327009070664644,
          -0.03281266242265701,
          0.04169667139649391,
          0.01020603347569704,
          -0.00896994024515152,
          0.008864178322255611,
          0.004650223068892956,
          -0.022434765473008156,
          -0.0020788845140486956,
          -0.0032703594770282507,
          -0.017450731247663498,
          0.01636666990816593,
          0.0065770745277404785,
          0.005595471244305372,
          -0.01890495792031288,
          -0.023783231154084206,
          0.010351455770432949,
          -0.018997499719262123,
          -0.010820775292813778,
          -0.03368519991636276,
          -0.04748713970184326,
          -0.008150284178555012,
          0.022923914715647697,
          -0.03548315167427063,
          0.008156894706189632,
          0.019513089209794998,
          0.025845589116215706,
          -0.013286352157592773,
          0.00865926407277584,
          -0.015494133345782757,
          -0.027127955108880997,
          0.03342079371213913,
          0.005747504066675901,
          -0.030988266691565514,
          -0.02515813708305359,
          -0.01573209837079048,
          -0.023360183462500572,
          -0.011521448381245136,
          0.055683694779872894,
          -0.0032158258836716413,
          0.03529806807637215,
          -0.019169364124536514,
          -0.027921169996261597,
          0.005331065971404314,
          -0.015917181968688965,
          -0.021734092384576797,
          -0.013577197678387165,
          -0.009042651392519474,
          0.015388371422886848,
          0.0035826878156512976,
          0.023320522159337997,
          0.023360183462500572,
          0.017450731247663498,
          -0.0016178281512111425,
          -0.014396852813661098,
          -0.009432649239897728,
          -0.022844593971967697,
          0.013438384979963303,
          -0.028873028233647346,
          -0.009492140263319016,
          -0.02261984907090664,
          -0.0066729215905070305,
          0.007892489433288574,
          0.006920801009982824,
          0.005526064895093441,
          -0.026731347665190697,
          -0.006120976060628891,
          0.007033173460513353,
          0.015428032726049423,
          -0.0005849960725754499,
          -0.00781977828592062,
          -5.628934741253033e-05,
          -0.002566381124779582,
          -0.02770964615046978,
          -0.008560112677514553,
          0.002556466031819582,
          -0.005879706237465143,
          0.004418868571519852,
          -0.006368855945765972,
          8.102567517198622e-05,
          -0.004385818261653185,
          0.010979417711496353,
          0.01834970712661743,
          0.02000223845243454,
          -0.02199849672615528,
          -0.02866150252521038,
          -0.08841703832149506,
          -0.0010402684565633535,
          0.023558486253023148,
          -0.028370657935738564,
          0.007733846548944712,
          0.003453790443018079,
          0.02009478025138378,
          0.004035481717437506,
          -0.016247687861323357,
          0.012400595471262932,
          -0.009935018606483936,
          0.012268392369151115,
          -0.014158888719975948,
          -0.021099520847201347,
          -0.02469542808830738,
          -0.02747168019413948,
          -0.02057071030139923,
          0.0006824954180046916,
          0.022210020571947098,
          0.0013955626636743546,
          -0.0005552505026571453,
          0.025303559377789497,
          0.010225864127278328,
          0.01771513558924198,
          -0.0328391008079052,
          -0.00472623948007822,
          -0.018852077424526215,
          0.006696057040244341,
          -0.004868357442319393,
          -0.01611548475921154,
          0.014436514116823673,
          -0.05007831007242203,
          -0.012916184961795807,
          -0.010622471570968628,
          -0.005572335794568062,
          -0.012215511873364449,
          -0.0066563962027430534,
          0.015150407329201698,
          0.005159202963113785,
          0.05573657527565956,
          -0.03246893733739853,
          -0.024007974192500114,
          0.01425143051892519,
          -0.0014534012880176306,
          -0.005826825276017189,
          0.020927656441926956,
          -0.002713456517085433,
          0.002300323685631156,
          0.01819106563925743,
          -0.008381638675928116,
          0.03558891639113426,
          0.01064230129122734,
          -0.0036190436221659184,
          -0.000224744260776788,
          -0.001570731052197516,
          -0.014595156535506248,
          0.0074826618656516075,
          0.011270263232290745,
          0.014991763979196548,
          -0.022196801379323006,
          0.028925908729434013,
          -0.004785730503499508,
          -0.0014178719138726592,
          -0.001155119389295578,
          0.0010154804913327098,
          -0.02412695810198784,
          -0.01856123097240925,
          -0.043309539556503296,
          0.017979539930820465,
          -0.010391117073595524,
          -0.021853074431419373,
          -0.002810955746099353,
          -0.008718755096197128,
          0.04161734879016876,
          -0.018243946135044098,
          0.008242825977504253,
          -0.012083308771252632,
          0.012268392369151115,
          -0.018944619223475456,
          -0.0039528547786176205,
          -0.01857445202767849,
          -0.009492140263319016,
          -0.00393302459269762,
          -0.01676327735185623,
          -0.013920923694968224,
          0.028767265379428864,
          -0.0016657515661790967,
          0.010239084251224995,
          0.007747066672891378,
          0.009022820740938187,
          -0.02246120572090149,
          0.02525067888200283,
          0.03437265008687973,
          -0.007290968205779791,
          -0.012757541611790657,
          0.023862551897764206,
          -9.125071665039286e-05,
          0.02039884589612484,
          0.023703908547759056,
          4.678729237639345e-05,
          0.00996806938201189,
          0.008950109593570232,
          0.001355901942588389,
          -0.007310798391699791,
          -0.0038867536932229996,
          0.00283739622682333,
          0.00861299317330122,
          -0.02406085655093193,
          0.003946244716644287,
          0.014819900505244732,
          -0.008520451374351978,
          -0.003177817678079009,
          -0.012645170092582703,
          0.02501271478831768,
          -0.016327008605003357,
          -0.009578071534633636,
          -0.002596126636490226,
          -0.008639433421194553,
          -0.02921675331890583,
          0.026096774265170097,
          -0.005621911492198706,
          0.017569713294506073,
          0.016141926869750023,
          -0.018468691036105156,
          0.050131190568208694,
          0.008546891622245312,
          0.02826489508152008,
          -0.00885756779462099,
          -0.0036719245836138725,
          -0.000804782728664577,
          -0.0033629012759774923,
          -0.0017153274966403842,
          -0.03529806807637215,
          -0.004554376471787691,
          -0.0015186762902885675,
          0.03595907986164093,
          0.004623782820999622,
          0.03254825621843338,
          -0.008361808955669403,
          0.06700023263692856,
          0.03278622031211853,
          -0.013121098279953003,
          0.026572704315185547,
          0.002539940644055605,
          0.01155449915677309,
          0.01856123097240925,
          0.004941068589687347,
          -0.005013780202716589,
          -0.009115362539887428,
          0.0031282417476177216,
          -0.015097525902092457,
          0.0010311795631423593,
          -0.04098277539014816,
          -0.027048632502555847,
          -0.003204258158802986,
          -0.02699575200676918,
          0.029560480266809464,
          -0.01528260949999094,
          0.026850329712033272,
          0.012625339441001415,
          -0.009954848326742649,
          -0.009545020759105682,
          -0.0048584421165287495,
          -0.016802938655018806,
          0.0013286351459100842,
          0.023148659616708755,
          -0.0066563962027430534,
          0.017847338691353798,
          -0.020544270053505898,
          -0.008474180474877357,
          0.00996806938201189,
          -0.014277870766818523,
          -0.02150934748351574,
          -0.015322270803153515,
          -0.020623590797185898,
          -0.02778896689414978,
          0.0055657257325947285,
          0.0017649034271016717,
          0.009545020759105682,
          -0.02277849242091179,
          0.012797202914953232,
          -0.011977546848356724,
          0.0037909068632870913,
          0.028000490739941597,
          0.005307930521667004,
          -0.0017814288148656487,
          0.023994754999876022,
          -0.003605823265388608
        ]
      }
    ]
  }
}