{
  "metadata": {
    "title": "네이버 밴드, 미국 학교서 통했다…MAU 껑충",
    "url": "https://zdnet.co.kr/view/?no=20241115110112",
    "date": "입력 :2024/11/15 11:41",
    "author": "안희정 기자",
    "category": "인터넷",
    "source": "zdnet",
    "created_at": "2025-05-08T09:11:14.753911"
  },
  "content": {
    "text": "네이버 밴드, 미국 학교서 통했다…MAU 껑충\n네이버의 그룹형 소셜 미디어 ‘밴드’가 국내에서 쌓은 그룹 커뮤니케이션 서비스 역량을 기반으로 글로벌 시장에서도 성과를 올리고 있다.\n네이버 밴드는 지난달 기준 미국 내 월간 활성 사용자 수(MAU) 604만 명으로 기록했다고 15일 밝혔다. 밴드는 미국 시장에서 2021년부터 매년 20% 이상 꾸준한 성장세를 이어오고 있으며, 작년 10월 500만 MAU를 돌파한 이후 1년 만에 100만 명의 사용자가 신규 유입됐다.\n밴드는 미국에서 학생, 학부모, 코치 간 체계적인 커뮤니케이션 니즈가 높은 학교와 ‘After School Activity(스포츠, 치어리딩, 댄스 등과 같은 방과후활동)’ 중심으로 빠르게 성장하였으며, 그룹 커뮤니케이션에 특화된 소셜 미디어로 인기를 얻고 있다. 현재 미국 내 활성 밴드의 65%가 학교 및 스포츠 그룹이며, 전체 활성 사용자 중 70% 이상이 해당 그룹의 밴드를 이용하고 있다. 미국 밴드 사용자 연령대 또한 10대와 40대가 각각 25%, 30대가 약 20%, 20대가 약 15%로 1040세대에 집중돼 있다.\n소셜미디어 경쟁이 치열한 미국 시장에서 밴드가 큰 인기를 얻은 배경에는 ‘그룹 커뮤니케이션’에 특화된 사용성이 있다. 밴드는 밴드 리더만 사용할 수 있는 기능을 제공하여 리더가 편리하게 그룹을 관리할 수 있도록 지원하며, 공지사항, 일정 관리, 초대장, 라이브 등 그룹 소통에 필요한 다양한 기능을 제공하고 있다. 또, 전화번호, 이메일, 다른 소셜미디어 계정 등 민감한 정보를 노출하지 않아도 그룹 활동에 참여할 수 있어  안전하게 사용할 수 있다.\n특히, 올해는 미국 시장에서 학교 및 방과후활동으로 시작된 밴드의 사용성이 다양한 업무 그룹(Work group)으로 확산되고 있다는 점이 주목된다. 업무 그룹에서 밴드를 사용하는 사용자는 지난해 대비 40% 이상 증가하였으며, 이들은 대부분 F&B, 소매업, 병의원, 물류/운송 기사부터 군인, 경찰, 소방관까지 오피스 환경이 아닌 현장에서 근무하거나 교대 근무를 수행하는 현장직(Front-Line Worker)으로, 실시간 소통이 중요한 환경에서 모바일에 최적화된 소셜 미디어인 밴드를 빠르고 편리한 그룹 커뮤니케이션 도구로 활용하고 있다.\n네이버 밴드US 채윤지 리더는 “밴드는 국내에서 쌓아온 그룹 커뮤니케이션 서비스 역량을 바탕으로 미국 방과후활동 시장에서 필수적인 그룹 커뮤니케이션 서비스로 자리매김했다”며 “앞으로도 그룹 커뮤니케이션 과정에서 발생하는 어려움을 해결하면서 방과후활동뿐만 아니라 다양한 워크 그룹에서 밴드를 업무에 적용하고 편리하게 활용할 수 있도록 지원할 계획”이라고 말했다.",
    "embeddings": [
      {
        "text": "네이버 밴드, 미국 학교서 통했다…MAU 껑충\n네이버의 그룹형 소셜 미디어 ‘밴드’가 국내에서 쌓은 그룹 커뮤니케이션 서비스 역량을 기반으로 글로벌 시장에서도 성과를 올리고 있다 네이버 밴드는 지난달 기준 미국 내 월간 활성 사용자 수(MAU) 604만 명으로 기록했다고 15일 밝혔다 밴드는 미국 시장에서 2021년부터 매년 20% 이상 꾸준한 성장세를 이어오고 있으며, 작년 10월 500만 MAU를 돌파한 이후 1년 만에 100만 명의 사용자가 신규 유입됐다 밴드는 미국에서 학생, 학부모, 코치 간 체계적인 커뮤니케이션 니즈가 높은 학교와 ‘After School Activity(스포츠, 치어리딩, 댄스 등과 같은 방과후활동)’ 중심으로 빠르게 성장하였으며, 그룹 커뮤니케이션에 특화된 소셜 미디어로 인기를 얻고 있다 현재 미국 내 활성 밴드의 65%가 학교 및 스포츠 그룹이며, 전체 활성 사용자 중 70% 이상이 해당 그룹의 밴드를 이용하고 있다 미국 밴드 사용자 연령대 또한 10대와 40대가 각각 25%, 30대가 약 20%, 20대가 약 15%로 1040세대에 집중돼 있다 소셜미디어 경쟁이 치열한 미국 시장에서 밴드가 큰 인기를 얻은 배경에는 ‘그룹 커뮤니케이션’에 특화된 사용성이 있다 밴드는 밴드 리더만 사용할 수 있는 기능을 제공하여 리더가 편리하게 그룹을 관리할 수 있도록 지원하며, 공지사항, 일정 관리, 초대장, 라이브 등 그룹 소통에 필요한 다양한 기능을 제공하고 있다 또, 전화번호, 이메일, 다른 소셜미디어 계정 등 민감한 정보를 노출하지 않아도 그룹 활동에 참여할 수 있어  안전하게 사용할 수 있다 특히, 올해는 미국 시장에서 학교 및 방과후활동으로 시작된 밴드의 사용성이 다양한 업무 그룹(Work group)으로 확산되고 있다는 점이 주목된다 업무 그룹에서 밴드를 사용하는 사용자는 지난해 대비 40% 이상 증가하였으며, 이들은 대부분 F&B, 소매업, 병의원, 물류/운송 기사부터 군인, 경찰, 소방관까지 오피스 환경이 아닌 현장에서 근무하거나 교대 근무를 수행하는 현장직(Front-Line Worker)으로, 실시간 소통이 중요한 환경에서 모바일에 최적화된 소셜 미디어인 밴드를 빠르고 편리한 그룹 커뮤니케이션 도구로 활용하고 있다 네이버 밴드US 채윤지 리더는 “밴드는 국내에서 쌓아온 그룹 커뮤니케이션 서비스 역량을 바탕으로 미국 방과후활동 시장에서 필수적인 그룹 커뮤니케이션 서비스로 자리매김했다”며 “앞으로도 그룹 커뮤니케이션 과정에서 발생하는 어려움을 해결하면서 방과후활동뿐만 아니라 다양한 워크 그룹에서 밴드를 업무에 적용하고 편리하게 활용할 수 있도록 지원할 계획”이라고 말했다.",
        "embedding": [
          -0.017616502940654755,
          -0.0012372073251754045,
          0.010920638218522072,
          -0.05083012208342552,
          -0.02200070209801197,
          0.006775578483939171,
          -0.01715151220560074,
          -0.013451515696942806,
          -0.010894066654145718,
          -0.004161666613072157,
          -0.02488364279270172,
          -0.015915965661406517,
          -5.854549272044096e-06,
          -0.007652417756617069,
          0.007021359167993069,
          0.0034708231687545776,
          0.014002861455082893,
          -0.00544371223077178,
          0.009073960594832897,
          -0.009313099086284637,
          -0.006895147264003754,
          0.008409688249230385,
          -0.020924579352140427,
          0.008542542345821857,
          -0.0025524666998535395,
          0.01737736538052559,
          -0.0033645397052168846,
          -0.02544163167476654,
          0.015039126388728619,
          0.020353306084871292,
          0.02382080815732479,
          -0.004291199613362551,
          4.325554982642643e-05,
          0.005317500326782465,
          -0.00736013799905777,
          -0.005500175524502993,
          0.010488861240446568,
          -0.033904463052749634,
          0.016168389469385147,
          0.00800448190420866,
          -0.001348472898826003,
          -0.016354385763406754,
          0.012568033300340176,
          0.0014962735585868359,
          -0.020805010572075844,
          0.026491181924939156,
          -0.003352914936840534,
          -0.0036534981336444616,
          0.00114254851359874,
          0.030157966539263725,
          0.025933193042874336,
          -0.007884913124144077,
          -0.016128532588481903,
          -0.0008618934080004692,
          -0.017948640510439873,
          -0.013949720188975334,
          -0.00800448190420866,
          0.018453486263751984,
          0.002291739685460925,
          -0.03525957837700844,
          -0.025454917922616005,
          0.02015402354300022,
          -0.026039477437734604,
          0.013723867014050484,
          -0.003533929120749235,
          -0.0017968567553907633,
          -0.023382388055324554,
          0.005257715936750174,
          -0.01595582254230976,
          -0.00410852488130331,
          0.022399265319108963,
          0.022465690970420837,
          0.018174491822719574,
          -0.018001781776547432,
          0.015384548343718052,
          -0.012508248910307884,
          -0.024020088836550713,
          0.004384197760373354,
          -0.0068021491169929504,
          -0.0014406407717615366,
          0.02154899574816227,
          -0.02589333802461624,
          -0.009525666013360023,
          0.015690114349126816,
          0.01153176836669445,
          0.021668564528226852,
          0.01244182139635086,
          0.019343610852956772,
          -0.007154213730245829,
          -0.00033587272628210485,
          0.011877190321683884,
          0.007087786216288805,
          0.00408527534455061,
          0.002429576124995947,
          0.009558879770338535,
          0.011564982123672962,
          -0.0277931559830904,
          0.007585990708321333,
          -0.0014564171433448792,
          0.00034521406632848084,
          0.002545823808759451,
          0.003264898667111993,
          -0.03616298735141754,
          -0.011352415196597576,
          -0.025707341730594635,
          -0.006161126308143139,
          -0.005453676450997591,
          -0.03164593502879143,
          0.020632300525903702,
          -0.016646666452288628,
          0.012521534226834774,
          0.024192800745368004,
          -0.01788221299648285,
          -0.024006804451346397,
          -0.012142899446189404,
          0.0044473037123680115,
          0.006612831726670265,
          -0.03265563026070595,
          0.01592925190925598,
          -0.00696157431229949,
          0.020645584911108017,
          0.014255285263061523,
          0.017536791041493416,
          -0.016022250056266785,
          0.011385628953576088,
          0.002794926054775715,
          0.003293130313977599,
          -0.024113086983561516,
          0.011418841779232025,
          -0.023050252348184586,
          0.04660534858703613,
          -0.009293170645833015,
          0.025335349142551422,
          0.0132655194029212,
          -0.014574135653674603,
          0.007386708632111549,
          0.01472027599811554,
          -0.0141888577491045,
          -0.025202494114637375,
          -0.028696566820144653,
          0.02048616111278534,
          0.013079523108899593,
          0.0029742796905338764,
          -0.036933545023202896,
          0.011471983976662159,
          0.03916550055146217,
          0.039537493139505386,
          0.025906622409820557,
          0.013830151408910751,
          0.009426024742424488,
          0.012767314910888672,
          -0.040733180940151215,
          0.011173061095178127,
          -0.008768395520746708,
          0.017364079132676125,
          -0.0040919180028140545,
          0.006330515723675489,
          0.03517986461520195,
          -0.021376285701990128,
          -0.006729079410433769,
          -0.022771257907152176,
          0.02728831022977829,
          0.015995679423213005,
          -0.005420462694019079,
          -0.00605152128264308,
          0.02997197024524212,
          -0.021788133308291435,
          -0.01962260529398918,
          0.007074500899761915,
          -0.0028314609080553055,
          -0.0033280046191066504,
          0.022731401026248932,
          -0.010568573139607906,
          -0.0011566643370315433,
          -0.020884724333882332,
          0.008768395520746708,
          0.007353495340794325,
          0.01211632788181305,
          -0.009286527521908283,
          -0.011611481197178364,
          -0.00017582459258846939,
          -0.01066157128661871,
          0.0025175923947244883,
          0.0158096831291914,
          -0.01363086886703968,
          0.004347662907093763,
          0.024192800745368004,
          0.007752058561891317,
          0.013165878131985664,
          -0.010960494168102741,
          0.01606210693717003,
          -0.004204844124615192,
          0.004527016077190638,
          -0.014321712777018547,
          -0.6113431453704834,
          0.021110575646162033,
          0.03241649270057678,
          0.02784629724919796,
          -0.022213269025087357,
          0.00891453493386507,
          0.02493678592145443,
          0.014069288969039917,
          -0.004407447297126055,
          0.019436608999967575,
          -0.021389570087194443,
          -0.00016513395530637354,
          0.0019977991469204426,
          -0.006636081263422966,
          -0.013185806572437286,
          -0.025481488555669785,
          -0.005161396227777004,
          -0.029785973951220512,
          0.020844867452979088,
          0.011385628953576088,
          -0.01939675398170948,
          0.00608805613592267,
          0.0032134177163243294,
          0.00856247078627348,
          -0.005038505885750055,
          0.02451165020465851,
          -0.0005579888238571584,
          -0.01469370536506176,
          -0.01631452888250351,
          0.02334253117442131,
          -0.023555098101496696,
          0.039032645523548126,
          0.029227985069155693,
          0.007466421462595463,
          0.052690085023641586,
          -0.0005260207108221948,
          -0.03042367473244667,
          0.01709837093949318,
          0.009352955035865307,
          0.013152592815458775,
          -0.025733912363648415,
          -0.01830734685063362,
          0.02068544179201126,
          -0.014507709071040154,
          0.017536791041493416,
          0.011478627100586891,
          0.004271271172910929,
          -0.0022103663068264723,
          0.021920988336205482,
          -0.023408958688378334,
          -0.023276103660464287,
          -0.006413549650460482,
          0.031114518642425537,
          0.010229794308543205,
          -0.0017005372792482376,
          0.024365510791540146,
          -0.013657440431416035,
          0.002306685782968998,
          0.014799988828599453,
          0.011212917976081371,
          -0.013219020329415798,
          -0.008097480051219463,
          -0.005174682009965181,
          -0.019011475145816803,
          -0.046897631138563156,
          0.03265563026070595,
          -0.022598545998334885,
          -0.01151848305016756,
          -0.0008224522462114692,
          -0.018679339438676834,
          -0.007957982830703259,
          -0.01388329267501831,
          0.00457019405439496,
          -0.010495503433048725,
          0.021336428821086884,
          0.03196478635072708,
          0.0526103712618351,
          -0.011684550903737545,
          -0.016659950837492943,
          0.019263898953795433,
          -0.018852049484848976,
          -0.014667133800685406,
          0.01006372645497322,
          -0.0006252463790588081,
          0.006659330800175667,
          0.015902681276202202,
          -0.012614532373845577,
          -0.017031943425536156,
          -0.004815974738448858,
          -0.021389570087194443,
          0.012435179203748703,
          0.020061025395989418,
          0.010216508992016315,
          -0.004915615543723106,
          0.0036468554753810167,
          0.028616854920983315,
          -0.007845057174563408,
          -0.01442799624055624,
          0.02645132690668106,
          0.0027749978471547365,
          -0.028537141159176826,
          0.016726378351449966,
          0.023993518203496933,
          -0.010694785043597221,
          0.006606188602745533,
          0.014334998093545437,
          -0.03512672334909439,
          -0.0336918942630291,
          0.04102546349167824,
          0.0015427726320922375,
          0.006433478090912104,
          0.007811843417584896,
          0.004633300006389618,
          0.001649886486120522,
          -0.0038660652935504913,
          -0.0242326557636261,
          0.020100882276892662,
          -0.005981772672384977,
          0.004238057881593704,
          0.0013368481304496527,
          0.01681937649846077,
          -0.01818777807056904,
          0.005327464547008276,
          -0.001398293417878449,
          -0.0011848958674818277,
          0.017563361674547195,
          0.010395863093435764,
          -0.017058514058589935,
          -0.01143212802708149,
          -0.011691194027662277,
          -0.01473356131464243,
          -0.006496584042906761,
          0.005051791667938232,
          -0.01091399509459734,
          0.040042340755462646,
          0.027580589056015015,
          0.01420214306563139,
          0.0052743228152394295,
          0.02885599248111248,
          -0.02096443623304367,
          -0.016301244497299194,
          -0.013358517549932003,
          -0.00091835658531636,
          -0.008628898300230503,
          -0.0007954661850817502,
          -0.0038826721720397472,
          -0.025733912363648415,
          0.026079334318637848,
          0.0022701509296894073,
          0.011491912417113781,
          0.007559419609606266,
          0.016527097672224045,
          -0.0144811375066638,
          0.017510220408439636,
          0.0041218101978302,
          -0.0006729909800924361,
          -0.008542542345821857,
          -0.006782221142202616,
          -0.015185266733169556,
          0.004234736319631338,
          -0.002794926054775715,
          0.009618664160370827,
          -0.012202683836221695,
          -0.03358561173081398,
          0.0022950610145926476,
          -0.03767753019928932,
          -0.003925849683582783,
          0.002283436246216297,
          0.023329246789216995,
          -0.024166230112314224,
          -0.006954931654036045,
          -7.358892617048696e-05,
          -0.017337508499622345,
          -0.0024428616743534803,
          0.02384737879037857,
          -0.009286527521908283,
          -0.004164987709373236,
          0.017390651628375053,
          -0.023236248642206192,
          -0.015039126388728619,
          0.00036202845512889326,
          0.0036933543160557747,
          -0.007526205852627754,
          -0.01497269980609417,
          0.02835114486515522,
          -0.00031822797609493136,
          0.004527016077190638,
          0.005699457135051489,
          -0.026212187483906746,
          0.010422433726489544,
          -0.0009997299639508128,
          0.02160213701426983,
          -0.019715603440999985,
          0.0026836604811251163,
          0.010362649336457253,
          -0.002167188562452793,
          -2.0784460502909496e-05,
          0.0007186596631072462,
          0.011498554609715939,
          0.020632300525903702,
          0.0027318201027810574,
          0.022718114778399467,
          0.01855977065861225,
          -0.0051514324732124805,
          0.014799988828599453,
          -0.011365700513124466,
          -0.00114254851359874,
          -0.01288688462227583,
          0.034329596906900406,
          -0.013790294528007507,
          0.030662812292575836,
          -0.029227985069155693,
          0.00034749749465845525,
          -0.032735344022512436,
          -0.030104823410511017,
          0.011591552756726742,
          -0.016301244497299194,
          0.009771446697413921,
          -0.014640563167631626,
          0.011113276705145836,
          -0.009970728307962418,
          0.0054868897423148155,
          0.02645132690668106,
          0.0023980233818292618,
          0.002050940878689289,
          -0.00517800310626626,
          0.009034104645252228,
          0.03632241487503052,
          0.020180594176054,
          -0.005091647617518902,
          -0.006729079410433769,
          0.02832457423210144,
          -0.0058422754518687725,
          0.018918476998806,
          0.006719115190207958,
          -0.016659950837492943,
          0.02989225648343563,
          -0.032894767820835114,
          0.014507709071040154,
          -0.024724217131733894,
          -0.016075391322374344,
          0.031273942440748215,
          0.039032645523548126,
          -0.014321712777018547,
          0.04676477611064911,
          -0.0160355344414711,
          -0.00470304861664772,
          -0.01671309396624565,
          -0.023103393614292145,
          0.0054968539625406265,
          -0.04158345237374306,
          0.007479706779122353,
          -0.0005596494884230196,
          -0.017138227820396423,
          -0.007552776951342821,
          -0.025534629821777344,
          0.0205393023788929,
          0.007479706779122353,
          0.01816120743751526,
          0.014627277851104736,
          0.011671265587210655,
          0.012740744277834892,
          -0.003200132166966796,
          -0.025840194895863533,
          -0.00863554049283266,
          0.0015519063454121351,
          0.013843436725437641,
          -0.01651381142437458,
          -0.018772337585687637,
          -0.02726173773407936,
          -0.012780600227415562,
          -0.014042718335986137,
          0.012900169938802719,
          -0.014534279704093933,
          -0.0010578538058325648,
          -0.017975211143493652,
          0.007253854535520077,
          -0.009538951329886913,
          -0.010103583335876465,
          0.004098560661077499,
          -0.02281111292541027,
          -0.021416140720248222,
          -0.009572165086865425,
          0.014520994387567043,
          -0.013431587256491184,
          -0.015331406146287918,
          -0.005520103499293327,
          -0.006519833579659462,
          -0.02983911521732807,
          -0.010515431873500347,
          -0.019104473292827606,
          0.016606809571385384,
          -0.014361568726599216,
          0.004762833006680012,
          -0.01470699068158865,
          -0.00968509167432785,
          0.013670725747942924,
          -0.008854750543832779,
          0.0006651027360931039,
          0.005563281010836363,
          0.027075741440057755,
          -0.0006115457508713007,
          -0.010993707925081253,
          -0.033240191638469696,
          0.008675397373735905,
          0.0006090547540225089,
          -0.016115248203277588,
          -0.0223859790712595,
          0.002894566860049963,
          -0.003909242805093527,
          -0.032257065176963806,
          -0.017457077279686928,
          -0.03456873446702957,
          0.008150622248649597,
          -0.015384548343718052,
          0.004962114617228508,
          -0.0043144491501152515,
          -0.02443193830549717,
          0.020353306084871292,
          -0.0021970809902995825,
          -0.019742175936698914,
          -0.004155023954808712,
          -0.01628795824944973,
          -0.015264979563653469,
          0.0668523758649826,
          -0.01967574842274189,
          -0.014786703512072563,
          0.01091399509459734,
          -0.021283287554979324,
          0.01301309559494257,
          -0.033240191638469696,
          -0.02776658535003662,
          -0.004922258201986551,
          0.0031569544225931168,
          0.00036202845512889326,
          0.006589582189917564,
          0.03103480488061905,
          -0.0008278494351543486,
          0.032815054059028625,
          0.024830501526594162,
          0.014839844778180122,
          -0.02681003324687481,
          0.008921178057789803,
          -0.015942536294460297,
          0.003332986729219556,
          -0.012866956181824207,
          0.014095859602093697,
          0.0357644259929657,
          0.045329947024583817,
          0.012760672718286514,
          -0.014281855896115303,
          0.030104823410511017,
          -0.011312558315694332,
          -0.022173412144184113,
          0.002829800359904766,
          -0.010468932799994946,
          -0.02627861499786377,
          0.01392314862459898,
          0.024113086983561516,
          0.03140679746866226,
          0.011392271146178246,
          0.004138417076319456,
          -0.011339129880070686,
          0.026637323200702667,
          0.04952814802527428,
          0.043390270322561264,
          -0.003293130313977599,
          -0.02028687857091427,
          0.0117576215416193,
          -0.004945507738739252,
          0.018772337585687637,
          -0.004613371565937996,
          -0.0025209137238562107,
          -0.02197412960231304,
          0.04293856769800186,
          -0.006828720215708017,
          -0.03246963396668434,
          -0.00661947438493371,
          0.0005310027627274394,
          -0.0170718003064394,
          -0.015690114349126816,
          0.009771446697413921,
          0.0029311019461601973,
          -0.018652768805623055,
          0.001273742294870317,
          -0.041158318519592285,
          0.02888256311416626,
          -0.01838705874979496,
          -0.01001722738146782,
          -0.029759403318166733,
          -0.018493343144655228,
          0.0001951300073415041,
          -0.0001115769991884008,
          0.02146928384900093,
          0.014946128241717815,
          -0.036986686289310455,
          -0.001533638802357018,
          -0.004337698686867952,
          0.02835114486515522,
          0.015517402440309525,
          0.04990014061331749,
          0.012827099300920963,
          -0.006460048723965883,
          0.0320710688829422,
          -0.00829676166176796,
          -0.005111576057970524,
          -0.015145409852266312,
          -0.02026030793786049,
          0.001810142188332975,
          0.02784629724919796,
          0.0033346472773700953,
          0.0059751300141215324,
          -0.026637323200702667,
          -0.008197121322154999,
          0.007798557635396719,
          -0.014295141212642193,
          0.0018666053656488657,
          -0.015039126388728619,
          0.010641643777489662,
          -0.0037265680730342865,
          -0.005702778231352568,
          0.0037199254147708416,
          0.016580238938331604,
          -0.004075311124324799,
          0.015769826248288155,
          -0.01699208840727806,
          -0.01914433017373085,
          0.0205393023788929,
          0.01150519773364067,
          0.011438770219683647,
          -0.0007726317853666842,
          0.004052061587572098,
          -0.006161126308143139,
          0.004749547690153122,
          0.02291739732027054,
          -0.010555287823081017,
          0.017868926748633385,
          -0.0017138227121904492,
          0.0029792615678161383,
          0.004052061587572098,
          0.019237328320741653,
          0.01897161826491356,
          0.02015402354300022,
          -0.016699807718396187,
          0.01323894876986742,
          -0.04665849357843399,
          0.02132314257323742,
          0.01679280586540699,
          -0.014228714630007744,
          0.02182799018919468,
          -0.022983824834227562,
          -0.03496729955077171,
          -0.01299981027841568,
          -0.006423513870686293,
          0.014786703512072563,
          0.007406637072563171,
          -0.009253314696252346,
          -0.022718114778399467,
          -0.025295492261648178,
          -0.010023870505392551,
          0.0063338372856378555,
          0.02334253117442131,
          -0.0027749978471547365,
          -0.007758701220154762,
          -0.018652768805623055,
          -0.009944157674908638,
          -0.005848918110132217,
          -0.005327464547008276,
          -0.010548645630478859,
          -0.023913806304335594,
          -0.016899090260267258,
          -0.006383657455444336,
          -0.03507358208298683,
          0.031114518642425537,
          -0.01643409952521324,
          -0.0031669186428189278,
          -0.0073999944142997265,
          -0.0050152563489973545,
          -0.001398293417878449,
          -0.009691733866930008,
          -0.021057434380054474,
          -0.005835632793605328,
          0.0424337200820446,
          0.02233283780515194,
          0.024365510791540146,
          0.0004633299831766635,
          0.005400534253567457,
          -0.008303404785692692,
          0.011339129880070686,
          -0.010209866799414158,
          -0.033877890557050705,
          0.0034774658270180225,
          0.0120499012991786,
          0.002416290808469057,
          0.0034110387787222862,
          0.034914154559373856,
          0.012362108565866947,
          0.00708114355802536,
          -0.0006119609461165965,
          0.03682726249098778,
          0.002198741538450122,
          -0.015264979563653469,
          -0.020074311643838882,
          -0.009233386255800724,
          0.003258256008848548,
          -0.030742526054382324,
          -0.03302762284874916,
          -0.009631949476897717,
          -0.045941077172756195,
          -0.02303696610033512,
          0.003430966753512621,
          0.019582750275731087,
          0.01972888968884945,
          0.011352415196597576,
          0.0005559129640460014,
          -0.02463121898472309,
          0.010668214410543442,
          0.03169907629489899,
          0.012488320469856262,
          -0.013803579844534397,
          -0.01790878362953663,
          -0.03624270111322403,
          -0.01939675398170948,
          -0.008794966153800488,
          0.02311667799949646,
          0.01145869866013527,
          0.0020791725255548954,
          -0.008203763514757156,
          0.007732130587100983,
          0.0043244133703410625,
          -0.03090195171535015,
          -0.03249620646238327,
          0.013318661600351334,
          -0.018852049484848976,
          -0.02440536767244339,
          -0.006373693700879812,
          0.016726378351449966,
          -0.012508248910307884,
          0.01917090080678463,
          0.008841465227305889,
          -0.025322062894701958,
          0.0034608591813594103,
          -0.01575654000043869,
          -0.001695555285550654,
          0.0144811375066638,
          0.015623686835169792,
          0.0382886603474617,
          0.007446493487805128,
          0.027195312082767487,
          0.006685901433229446,
          0.02516263723373413,
          -0.02160213701426983,
          0.004942186642438173,
          -0.006131234113126993,
          -0.0240998025983572,
          0.013192449696362019,
          0.007911483757197857,
          -0.03568471223115921,
          0.008236977271735668,
          0.00676561426371336,
          0.0016698146937415004,
          -0.018626198172569275,
          -0.02650446817278862,
          0.05728685110807419,
          -0.0017503576818853617,
          0.002248561941087246,
          -0.017470363527536392,
          0.001450604759156704,
          -0.013843436725437641,
          0.034382738173007965,
          0.00517800310626626,
          -0.0005334937595762312,
          0.023196391761302948,
          -0.028563711792230606,
          0.0004284556780476123,
          0.04028147831559181,
          -0.008595684543251991,
          0.00516471778973937,
          0.00572270667180419,
          -0.014879701659083366,
          -0.0003753138880711049,
          -0.015078983269631863,
          -0.0051514324732124805,
          0.004463910590857267,
          -0.022412549704313278,
          0.014866415411233902,
          -0.006722436286509037,
          0.013464801013469696,
          0.025043068453669548,
          -0.0063172304071486,
          -0.011392271146178246,
          -0.00470304861664772,
          -0.02443193830549717,
          0.03730553761124611,
          -0.006828720215708017,
          0.0005745955859310925,
          0.005490211304277182,
          0.004968757275491953,
          0.021416140720248222,
          -0.003590392181649804,
          -0.007805200293660164,
          -0.013670725747942924,
          -0.03199135884642601,
          -0.0016465651569887996,
          0.0015817986568436027,
          0.00048740985221229494,
          -0.02129657194018364,
          0.024551507085561752,
          -0.004928900860249996,
          -0.013371802866458893,
          -0.020565873011946678,
          -0.009658520109951496,
          0.025229064747691154,
          0.031805362552404404,
          0.002829800359904766,
          -0.0193701833486557,
          -0.015876110643148422,
          0.02936084009706974,
          -0.03977663069963455,
          -0.015942536294460297,
          0.006260767113417387,
          0.006709150969982147,
          -0.018240919336676598,
          0.02210698463022709,
          0.010050441138446331,
          0.0015452635707333684,
          -0.00499532837420702,
          0.011312558315694332,
          0.0066327597014606,
          -0.03882007673382759,
          0.025654198601841927,
          -0.01939675398170948,
          -0.014667133800685406,
          -0.0015303174732252955,
          -0.007047929801046848,
          0.012900169938802719,
          0.0020276913419365883,
          -0.0036103203892707825,
          0.010462289676070213,
          -0.00318352528847754,
          0.0011956902453675866,
          -0.0024843786377459764,
          -0.008137336932122707,
          -0.00762584712356329,
          -0.022346122190356255,
          0.004815974738448858,
          0.012594603933393955,
          0.006310587748885155,
          -0.027926011011004448,
          -0.01444128155708313,
          0.005094969179481268,
          -0.009558879770338535,
          -0.03204450011253357,
          -0.0038660652935504913,
          -0.014388139359652996,
          0.0288294218480587,
          -0.007220640778541565,
          -0.0029659762512892485,
          -0.02339567244052887,
          -0.0029792615678161383,
          -0.03244306147098541,
          0.017789214849472046,
          0.0014672116376459599,
          0.011890475638210773,
          0.014507709071040154,
          0.008124051615595818,
          0.004835902713239193,
          0.0199547428637743,
          -0.001868266030214727,
          -0.021681850776076317,
          -0.013790294528007507,
          -0.020313449203968048,
          -0.011093349196016788,
          0.0016648327000439167,
          0.011571625247597694,
          0.036030132323503494,
          -0.0051514324732124805,
          -0.00796462595462799,
          -0.01441471092402935,
          0.005440390668809414,
          -0.06722436845302582,
          0.006400264333933592,
          0.014866415411233902,
          0.02703588642179966,
          -0.01793535426259041,
          -0.011644694954156876,
          -0.00519128842279315,
          0.004895687568932772,
          -0.0170718003064394,
          0.01939675398170948,
          -0.013657440431416035,
          -0.01066157128661871,
          0.016752948984503746,
          0.0018549805972725153,
          0.022399265319108963,
          -0.021867847070097923,
          -0.04758847504854202,
          0.00706785824149847,
          0.002657089615240693,
          -0.005065076984465122,
          -0.0026188937481492758,
          0.04110517352819443,
          -0.0048990086652338505,
          -0.009731590747833252,
          0.03563157096505165,
          0.005835632793605328,
          -0.004171630367636681,
          -0.011239488609135151,
          0.04410768672823906,
          -0.019038045778870583,
          -0.006154483649879694,
          0.013165878131985664,
          -0.012494963593780994,
          -0.017284367233514786,
          0.0009150351979769766,
          0.009665163233876228,
          0.010575216263532639,
          0.03640212491154671,
          0.020552586764097214,
          -0.009220100939273834,
          0.01780249923467636,
          0.00013565686822403222,
          0.026159046217799187,
          -0.0034741444978863,
          0.020393162965774536,
          0.04469224438071251,
          0.013258876278996468,
          -0.022518834099173546,
          -0.00281319348141551,
          0.01909118890762329,
          -0.003120419569313526,
          -0.012156184762716293,
          0.005991736892610788,
          -0.02633175626397133,
          0.019157614558935165,
          -0.00199447781778872,
          0.02655760943889618,
          -0.0025707341264933348,
          -0.0029144950676709414,
          -0.0022286337334662676,
          -0.017669646069407463,
          -0.021987415850162506,
          0.011897118762135506,
          7.447116331604775e-06,
          -0.024750789627432823,
          -0.005397213157266378,
          0.007984554395079613,
          -0.009784732013940811,
          -0.004905651323497295,
          -0.015623686835169792,
          0.02986568585038185,
          -0.02079172618687153,
          -0.016394242644309998,
          0.054257769137620926,
          -0.00543042691424489,
          -0.00720071280375123,
          0.014095859602093697,
          0.024471795186400414,
          0.002705249236896634,
          0.013112736865878105,
          0.2482784390449524,
          -0.0004687272012233734,
          0.012820457108318806,
          0.02997197024524212,
          -0.006413549650460482,
          0.017789214849472046,
          0.007825128734111786,
          0.01442799624055624,
          0.007957982830703259,
          -0.013976290822029114,
          -0.04317770525813103,
          0.008642183616757393,
          0.005187967326492071,
          -0.015450975857675076,
          0.001535299583338201,
          -0.01646067015826702,
          -0.027660302817821503,
          -0.023767665028572083,
          -0.006200982723385096,
          0.014241999946534634,
          0.005792455282062292,
          -0.00850932952016592,
          -0.004523694980889559,
          0.0021788133308291435,
          0.016726378351449966,
          0.019051332026720047,
          -0.02311667799949646,
          0.026318471878767014,
          0.004334377124905586,
          0.018267489969730377,
          -0.007008073385804892,
          -0.001666493364609778,
          -0.018121350556612015,
          0.01473356131464243,
          -0.025880051776766777,
          -0.0006771426415070891,
          0.02538849040865898,
          -0.01676623523235321,
          -0.0018234277376905084,
          0.030769096687436104,
          0.004005562514066696,
          0.021788133308291435,
          0.006968217436224222,
          -0.02040644735097885,
          0.014640563167631626,
          0.006915075704455376,
          0.008848108351230621,
          -0.0021240110509097576,
          -0.01922404207289219,
          0.010429075919091702,
          -0.0002740123600233346,
          -0.011119919829070568,
          0.0038826721720397472,
          0.020419733598828316,
          0.007605918683111668,
          -0.0012662692461162806,
          -0.020645584911108017,
          0.004686441738158464,
          -0.01244182139635086,
          0.012215969152748585,
          -0.0009382847347296774,
          0.024166230112314224,
          -0.02384737879037857,
          0.01572996936738491,
          -0.017948640510439873,
          -0.03557842969894409,
          0.009007533080875874,
          0.016646666452288628,
          -0.0018450164934620261,
          -0.008369832299649715,
          -0.02496335655450821,
          -0.0058522396720945835,
          -0.010123510845005512,
          0.011345772072672844,
          -0.023156534880399704,
          -0.03719925507903099,
          0.0299985408782959,
          0.02944055199623108,
          0.03480787202715874,
          0.029626548290252686,
          -0.013604298233985901,
          0.010701428167521954,
          -0.0010561931412667036,
          0.011040206998586655,
          0.009313099086284637,
          -0.013331946916878223,
          -0.004530337639153004,
          -0.004168309271335602,
          -0.007233926095068455,
          -0.026358328759670258,
          0.010953851975500584,
          0.028988847509026527,
          -0.01684594713151455,
          -0.01440142560750246,
          -0.00890124961733818,
          0.017138227820396423,
          0.017510220408439636,
          0.010814354754984379,
          -0.020751869305968285,
          0.0004342680622357875,
          -0.01351794321089983,
          0.03634898364543915,
          0.03377160802483559,
          0.029520263895392418,
          -0.01322566345334053,
          -0.021668564528226852,
          -0.008263548836112022,
          0.025614343583583832,
          0.006994788069278002,
          -0.009200172498822212,
          -0.009864444844424725,
          -0.031167659908533096,
          0.007665703073143959,
          -0.0012878581183031201,
          0.015012555755674839,
          0.020805010572075844,
          -0.014029433019459248,
          -0.004613371565937996,
          0.00037406838964670897,
          -0.01964917778968811,
          -0.0016972159501165152,
          -0.0387403666973114,
          -0.0009864445310086012,
          -0.0056297085247933865,
          0.006968217436224222,
          0.0009117138688452542,
          -0.008197121322154999,
          0.011106634512543678,
          -0.014388139359652996,
          -0.04843874275684357,
          -0.017244510352611542,
          -0.03212421387434006,
          0.03672097623348236,
          -0.03246963396668434,
          -0.016726378351449966,
          0.007984554395079613,
          -0.0076391324400901794,
          -0.00636705057695508,
          0.00630394509062171,
          0.010814354754984379,
          -0.010960494168102741,
          -0.00918024405837059,
          0.027952581644058228,
          -0.0033280046191066504,
          0.0033877892419695854,
          -0.05213209614157677,
          0.007665703073143959,
          0.019848458468914032,
          -0.00863554049283266,
          0.006612831726670265,
          -0.008854750543832779,
          0.013325303792953491,
          -0.019303755834698677,
          -0.02549477480351925,
          0.03100823424756527,
          -0.0015942536992952228,
          -0.04368255287408829,
          -0.03767753019928932,
          0.003004171885550022,
          0.005825668573379517,
          -0.02146928384900093,
          -0.013232305645942688,
          0.053859204053878784,
          -0.04827931523323059,
          -0.016633380204439163,
          0.008349903859198093,
          -0.16814061999320984,
          0.020805010572075844,
          0.02485707215964794,
          0.011418841779232025,
          -0.0014464531559497118,
          -0.00947252381592989,
          0.008841465227305889,
          -0.0010155064519494772,
          -0.017842356115579605,
          0.00681543443351984,
          0.021641993895173073,
          -0.013159235939383507,
          -0.013159235939383507,
          -0.012275753542780876,
          -0.012900169938802719,
          0.02068544179201126,
          -0.0007581008248962462,
          0.00445062480866909,
          0.008422973565757275,
          0.005271001253277063,
          0.033877890557050705,
          -0.006626117043197155,
          -0.023196391761302948,
          0.006612831726670265,
          0.002429576124995947,
          0.0037498176097869873,
          0.006151162087917328,
          0.0085359001532197,
          -0.008323333226144314,
          -0.020313449203968048,
          -0.012269110418856144,
          0.0030456888489425182,
          0.018626198172569275,
          -0.015583829954266548,
          0.008708611130714417,
          0.024245942011475563,
          -0.008329975418746471,
          -0.02706245705485344,
          -0.007585990708321333,
          0.03871379420161247,
          0.010096940211951733,
          0.012661031447350979,
          0.007845057174563408,
          0.0288294218480587,
          -0.008064266294240952,
          0.0012878581183031201,
          0.024418652057647705,
          0.02465779148042202,
          -0.002696945797652006,
          1.0145722626475617e-05,
          -0.015424404293298721,
          -0.0288294218480587,
          0.02776658535003662,
          0.01972888968884945,
          -0.003251613350585103,
          0.033824749290943146,
          0.01699208840727806,
          -0.00169140356592834,
          -0.004998649470508099,
          -0.009020819328725338,
          -0.017443792894482613,
          -0.0008859732770361006,
          0.02023373730480671,
          -0.003879350610077381,
          -0.01987502910196781,
          -0.022266410291194916,
          -0.017005372792482376,
          0.007951340638101101,
          -0.03762438893318176,
          -0.00823033507913351,
          -0.005344071425497532,
          0.01063500065356493,
          0.013856722041964531,
          -0.020725298672914505,
          0.011212917976081371,
          0.00909388903528452,
          -0.0027318201027810574,
          0.0072937109507620335,
          -0.008070909418165684,
          0.01143212802708149,
          0.016075391322374344,
          0.020951149985194206,
          -0.007918126881122589,
          0.009286527521908283,
          -0.004540301859378815,
          0.009778089821338654,
          0.01499927043914795,
          0.017948640510439873,
          0.006071449723094702,
          -0.00034604439861141145,
          0.019077902659773827,
          -0.0019230685429647565,
          -0.013737153261899948,
          -0.014786703512072563,
          0.02655760943889618,
          0.011206274852156639,
          -0.009399454109370708,
          0.007174141705036163,
          -0.01441471092402935,
          -0.020047741010785103,
          -0.009233386255800724,
          -0.0065729753114283085,
          -0.04086603596806526,
          0.0014605688629671931,
          0.03887321799993515,
          -0.007698916830122471,
          0.016354385763406754,
          0.0007572704926133156,
          0.033266760408878326,
          -0.01816120743751526,
          -0.0052543943747878075,
          -0.017058514058589935,
          0.05935937911272049,
          0.008329975418746471,
          0.009366240352392197,
          0.014760131947696209,
          -0.01939675398170948,
          -0.014228714630007744,
          0.0063338372856378555,
          0.020977722480893135,
          0.06451413035392761,
          -0.010615072213113308,
          -0.026624036952853203,
          -0.007984554395079613,
          0.011026921682059765,
          -0.016075391322374344,
          -0.07232597470283508,
          -0.019914885982871056,
          0.015065697953104973,
          0.0054868897423148155,
          -0.01998131349682808,
          0.0007859172765165567,
          -0.005971808917820454,
          0.017138227820396423,
          -0.012654389254748821,
          0.02116371877491474,
          -0.021283287554979324,
          -0.019263898953795433,
          -0.009459238499403,
          -0.006280695553869009,
          0.015158696100115776,
          0.011983473785221577,
          0.013763723894953728,
          -0.02673032134771347,
          -0.004221451003104448,
          0.02157556638121605,
          0.02146928384900093,
          -0.015490831807255745,
          -0.006523154675960541,
          -0.01322566345334053,
          -0.010249722748994827,
          0.002250222722068429,
          -0.022213269025087357,
          0.04976728558540344,
          0.015942536294460297,
          0.003922528587281704,
          -0.0030290819704532623,
          -0.023222962394356728,
          0.027142168954014778,
          -0.010435719043016434,
          0.009598735719919205,
          -0.008708611130714417,
          -0.01762978918850422,
          -0.013697296380996704,
          0.029095130041241646,
          -0.030715955421328545,
          0.005520103499293327,
          0.015318120829761028,
          -0.016620095819234848,
          -0.0408128947019577,
          -0.00722728343680501,
          -0.002901209518313408,
          0.0021206894889473915,
          0.02255868911743164,
          -0.007087786216288805,
          -0.004503766540437937,
          0.007546134293079376,
          -0.021509138867259026,
          -0.03677411749958992,
          -0.03834180161356926,
          0.00934631284326315,
          0.00212733238004148,
          0.025202494114637375,
          -0.01177090685814619,
          -0.03377160802483559,
          -0.00014271476538851857,
          0.011970188468694687,
          -0.0004537810746114701,
          -0.007021359167993069,
          -0.003440930973738432,
          0.020313449203968048,
          0.014773417264223099,
          0.0067921848967671394,
          0.020619014278054237,
          0.007951340638101101,
          -0.005410498473793268,
          0.007599276024848223,
          0.011956903152167797,
          -0.028483999893069267,
          0.022093700245022774,
          -0.04509080946445465,
          0.0032715415582060814,
          -0.04155687987804413,
          -0.001753679127432406,
          0.008868035860359669,
          0.015597115270793438,
          -0.018240919336676598,
          -0.0120499012991786,
          0.0019994599279016256,
          0.014295141212642193,
          0.014308427460491657,
          -0.004068668466061354,
          0.009226743131875992,
          0.024564793333411217,
          -0.0032715415582060814,
          -0.028749708086252213,
          0.001352624618448317,
          0.01474684663116932,
          0.0021954202093183994,
          -0.0015120500465855002,
          -0.010296221822500229,
          0.0022900791373103857,
          0.000442571472376585,
          -0.010495503433048725,
          -0.010820996947586536,
          0.017536791041493416,
          -0.002881281543523073,
          -0.009678448550403118,
          -0.0733356699347496,
          0.01442799624055624,
          0.01497269980609417,
          -0.012395322322845459,
          -0.006828720215708017,
          -0.014268570579588413,
          -0.0035771068651229143,
          0.0006713302573189139,
          -0.01785564236342907,
          0.009798017330467701,
          -0.010528717190027237,
          0.003258256008848548,
          0.006672616116702557,
          -0.009240028448402882,
          -0.03876693546772003,
          -0.027952581644058228,
          0.04782761260867119,
          0.009240028448402882,
          0.01207647193223238,
          0.02661075070500374,
          -0.0019695675000548363,
          0.003982312977313995,
          0.05292922258377075,
          -0.0012795546790584922,
          -0.026371613144874573,
          0.029679689556360245,
          -0.04246028885245323,
          0.02233283780515194,
          0.00647333450615406,
          -0.02936084009706974,
          0.00622091069817543,
          -0.020340019837021828,
          -0.0009042407618835568,
          -0.0059850942343473434,
          0.018068209290504456,
          -0.036933545023202896,
          0.0008129033376462758,
          0.01911775954067707,
          0.005569924134761095,
          0.029706260189414024,
          -0.004975399933755398,
          -0.028616854920983315,
          0.008329975418746471,
          -0.01944989524781704,
          -0.022292980924248695,
          0.0001232017675647512,
          -0.009678448550403118,
          0.003266559448093176,
          0.004845866933465004,
          -0.014255285263061523,
          0.03661469370126724,
          -0.0028762994334101677,
          -0.00529757235199213,
          -0.04418740049004555,
          0.009771446697413921,
          -0.017961924895644188,
          0.012601247057318687,
          0.014653848484158516,
          0.013285447843372822,
          -0.014507709071040154,
          0.01654038205742836,
          -0.0002484793949406594,
          0.02091129496693611,
          -0.0008203763864003122,
          -0.0030157966539263725,
          -0.015876110643148422,
          -0.017762644216418266,
          0.0002688227395992726,
          0.015397833660244942,
          -0.027607159689068794,
          -0.0011931993067264557,
          -0.005094969179481268,
          0.004713012371212244,
          0.022997109219431877,
          -0.012827099300920963,
          -0.003523964900523424,
          -0.006656009238213301,
          0.008456187322735786,
          -0.028696566820144653,
          0.02160213701426983,
          -0.02731488086283207,
          -0.01497269980609417,
          -0.0067921848967671394,
          0.00941938254982233,
          0.006453406065702438,
          0.020592443645000458,
          -0.03262905776500702,
          0.011099991388618946,
          0.009924229234457016,
          -0.0076324897818267345,
          -0.06127248331904411,
          0.011930331587791443,
          0.023475386202335358,
          0.011372342705726624,
          -0.008768395520746708,
          0.028005722910165787,
          -0.0003742759581655264,
          0.001919747213833034,
          0.012289038859307766,
          0.010103583335876465,
          0.013232305645942688,
          -0.007758701220154762,
          -0.005134825594723225,
          -0.023860663175582886,
          -0.011923689395189285,
          0.00398895563557744,
          -0.011046850122511387,
          -0.013391731306910515,
          -0.019237328320741653,
          0.02496335655450821,
          -0.007805200293660164,
          0.01150519773364067,
          -0.016633380204439163,
          0.023276103660464287,
          -0.014361568726599216,
          0.012893526814877987,
          0.01007701177150011,
          -0.005732670426368713,
          -0.03406388685107231,
          0.029626548290252686,
          0.011398914270102978,
          0.026145759969949722,
          0.022651687264442444,
          -0.022691544145345688,
          0.04235400632023811,
          0.00825690571218729,
          0.022452406585216522,
          -0.018254205584526062,
          0.016048820689320564,
          -0.01922404207289219,
          -0.010747927241027355,
          -0.0038361730985343456,
          -0.0015112196560949087,
          -0.014773417264223099,
          -0.015450975857675076,
          0.012056543491780758,
          0.0068220775574445724,
          -0.004958793520927429,
          -0.010216508992016315,
          0.07089114934206009,
          0.0320710688829422,
          0.01567682810127735,
          -0.0029261198360472918,
          0.0017918747616931796,
          0.012601247057318687,
          0.04078632593154907,
          -0.00458347937092185,
          0.0036601407919079065,
          -0.010654929094016552,
          0.013491371646523476,
          -0.018201062455773354,
          -0.008894607424736023,
          -0.05080355331301689,
          -0.022930681705474854,
          0.016620095819234848,
          -0.009924229234457016,
          0.04402797296643257,
          -0.03831522911787033,
          0.006373693700879812,
          0.015384548343718052,
          -0.017975211143493652,
          0.020619014278054237,
          0.002341560088098049,
          -0.013484729453921318,
          -0.016978802159428596,
          0.0026338400784879923,
          -0.010223152115941048,
          -0.007732130587100983,
          -0.020831581205129623,
          0.01090070977807045,
          0.0026604109443724155,
          -0.038607511669397354,
          -0.006675937213003635,
          -0.013491371646523476,
          -0.0028331216890364885,
          -0.01922404207289219,
          -0.00027484269230626523,
          0.01699208840727806,
          0.004155023954808712,
          -0.00856247078627348,
          -0.0005247751832939684,
          -0.012554747983813286,
          0.002183795440942049,
          0.01732422411441803,
          -0.01777592860162258,
          -0.027713444083929062,
          -0.002919477177783847,
          -0.018254205584526062
        ]
      }
    ]
  }
}