{
  "metadata": {
    "title": "과방위, AI 강국 도약을 위한 성명서 합의…\"국가 차원 지원\"",
    "url": "https://zdnet.co.kr/view/?no=20250219101031",
    "date": "입력 :2025/02/19 11:28",
    "author": "안희정 기자",
    "category": "인터넷",
    "source": "zdnet",
    "created_at": "2025-05-08T03:17:17.376477"
  },
  "content": {
    "text": "과방위, AI 강국 도약을 위한 성명서 합의…\"국가 차원 지원\"\n국회가 대한민국이 AI 강국으로 도약할 수 있도록 정책적 지원을 아끼지 않겠다는 내용의 여야 합의 성명서를 공개했다.\n국회 과학기술정보방송통신위원회 소속 위원들은 19일 경기도 네이버 본사를 방문해 인공지능(AI) 관련 기술 시연을 참관하고, AI 관련 성명서를 발표했다.\n이번 현장에는 최민희 과방위원장을 비롯한 10명의 과방위원들과 국회 과방위 관계자들이 참석했으며, 네이버의 생성형 AI 연구개발 현황을 듣고, 최신 로봇 기술이 적용된 서비스 시연을 직접 참관하는 시간을 가졌다.\n네이버 측은 AI 검색과 생성형 AI, 로보틱스 기술 등 다양한 분야에서의 성과를 소개하고 AI 관련 혁신을 위한 지속적인 연구개발 계획을 공유했다. 과방위원들은 AI 기술 발전이 국가 경쟁력 강화에 미치는 영향에 대해 깊이 공감하며, 대한민국이 AI 강국으로 도약하기 위한 정책적 지원방안을 논의했다.\n특히, AI 산업 활성화를 위해 대규모 인프라 투자가 중요하고, 이를 위해서는 입법과 정책적 노력이 필요하다는데 의견을 모았다.\n이에 따라 과방위 위원들은 AI 강국으로의 도약을 위한 지원 의지를 담아 여야 합의 성명서를 발표했다. 성명서에는 ▲ AI 대규모 투자 및 인프라 조성 ▲ AI 산업계와의 소통 강화 ▲ AI 법·제도 정비 및 국제협력 확대 ▲ 예산 투입 등 후속조치의 신속한 추진 등의 내용이 포함됐다.\n최민희 위원장은 “AI 기술이 대한민국의 미래를 결정짓는 중요한 요소인 만큼 과방위가 앞장서서 정부, 기업과 협력해 AI 3대 강국으로 도약할 수 있도록 정책적 지원을 아끼지 않겠다”라고 밝혔다.\n국회 과방위는 앞으로도 AI 관련 기업 및 연구기관과의 소통을 확대하고 AI 산업 발전을 위한 정책 마련에 적극 나설 방침이다.\n다음은 여야 합의 성명서\nAI 강국 대한민국, 국회 과방위가 앞장서겠습니다.\n국회 과학기술정보방송통신위원회는 대한민국이 AI 강국으로 도약할 수 있도록 정책적 지원과 제도 정비에 적극 나서겠습니다.\n첫째, AI 대규모 투자 및 인프라를 조성하겠습니다. 국가 차원의 AI 지원 체계를 구축하고, 연구·개발을 촉진하며, 국내외 인재를 육성하고 유치할 수 있는 환경을 마련하겠습니다. 또한, 기업과 연구기관이 자유롭게 도전할 수 있는 혁신 생태계를 조성하겠습니다.\n둘째, AI 산업계와 지속적인 소통을 강화하겠습니다. 산업계·전문가·정부와 협력해 현장의 의견을 정책에 반영하고, AI 관련 규제를 개선하며, 기술발전을 촉진하는 지원방안을 구체화하겠습니다.\n셋째, AI 법·제도를 정비하고 국제협력을 확대하겠습니다. AI 산업의 윤리적·법적 기반을 강화하기 위해 법·제도를 정비하고, 글로벌 AI 규범이 빠르게 정립되고 있는 만큼, 국제 협력과 기술 교류를 확대하여 우리나라가 국제 AI 시장에서 주도적인 역할을 할 수 있도록 지원하겠습니다. 또한, 글로벌 AI 거버넌스 구축에 기여하고, 주요국과의 협력을 통해 우리 기업이 해외 시장에서도 경쟁력을 갖출 수 있도록 정책적 지원을 아끼지 않겠습니다.\n넷째, AI 강국으로 가기 위한 지원을 아끼지 않겠습니다. AI 산업의 발전과 글로벌 경쟁에서 뒤처지지 않기 위해선 지금이 골든타임입니다. AI 기본법의 취지에 맞춰 필요한 추가 예산이 적기에 투입될 수 있도록 하겠습니다. 이를 위해 추경 편성을 포함한 모든 후속 조치를 신속히 추진하여, 대한민국이 AI 강국으로 도약할 수 있도록 적극 뒷받침하겠습니다.\n앞으로 국회 과방위는 AI 산업의 성장 기반을 조성하고, 대한민국이 AI 선도국으로 도약할 수 있도록 필요한 모든 정책적 노력을 기울이겠습니다.",
    "embeddings": [
      {
        "text": "과방위, AI 강국 도약을 위한 성명서 합의…\"국가 차원 지원\"\n국회가 대한민국이 AI 강국으로 도약할 수 있도록 정책적 지원을 아끼지 않겠다는 내용의 여야 합의 성명서를 공개했다 국회 과학기술정보방송통신위원회 소속 위원들은 19일 경기도 네이버 본사를 방문해 인공지능(AI) 관련 기술 시연을 참관하고, AI 관련 성명서를 발표했다 이번 현장에는 최민희 과방위원장을 비롯한 10명의 과방위원들과 국회 과방위 관계자들이 참석했으며, 네이버의 생성형 AI 연구개발 현황을 듣고, 최신 로봇 기술이 적용된 서비스 시연을 직접 참관하는 시간을 가졌다 네이버 측은 AI 검색과 생성형 AI, 로보틱스 기술 등 다양한 분야에서의 성과를 소개하고 AI 관련 혁신을 위한 지속적인 연구개발 계획을 공유했다 과방위원들은 AI 기술 발전이 국가 경쟁력 강화에 미치는 영향에 대해 깊이 공감하며, 대한민국이 AI 강국으로 도약하기 위한 정책적 지원방안을 논의했다 특히, AI 산업 활성화를 위해 대규모 인프라 투자가 중요하고, 이를 위해서는 입법과 정책적 노력이 필요하다는데 의견을 모았다 이에 따라 과방위 위원들은 AI 강국으로의 도약을 위한 지원 의지를 담아 여야 합의 성명서를 발표했다 성명서에는 ▲ AI 대규모 투자 및 인프라 조성 ▲ AI 산업계와의 소통 강화 ▲ AI 법·제도 정비 및 국제협력 확대 ▲ 예산 투입 등 후속조치의 신속한 추진 등의 내용이 포함됐다 최민희 위원장은 “AI 기술이 대한민국의 미래를 결정짓는 중요한 요소인 만큼 과방위가 앞장서서 정부, 기업과 협력해 AI 3대 강국으로 도약할 수 있도록 정책적 지원을 아끼지 않겠다”라고 밝혔다 국회 과방위는 앞으로도 AI 관련 기업 및 연구기관과의 소통을 확대하고 AI 산업 발전을 위한 정책 마련에 적극 나설 방침이다 다음은 여야 합의 성명서\nAI 강국 대한민국, 국회 과방위가 앞장서겠습니다 국회 과학기술정보방송통신위원회는 대한민국이 AI 강국으로 도약할 수 있도록 정책적 지원과 제도 정비에 적극 나서겠습니다 첫째, AI 대규모 투자 및 인프라를 조성하겠습니다 국가 차원의 AI 지원 체계를 구축하고, 연구·개발을 촉진하며, 국내외 인재를 육성하고 유치할 수 있는 환경을 마련하겠습니다 또한, 기업과 연구기관이 자유롭게 도전할 수 있는 혁신 생태계를 조성하겠습니다 둘째, AI 산업계와 지속적인 소통을 강화하겠습니다 산업계·전문가·정부와 협력해 현장의 의견을 정책에 반영하고, AI 관련 규제를 개선하며, 기술발전을 촉진하는 지원방안을 구체화하겠습니다 셋째, AI 법·제도를 정비하고 국제협력을 확대하겠습니다 AI 산업의 윤리적·법적 기반을 강화하기 위해 법·제도를 정비하고, 글로벌 AI 규범이 빠르게 정립되고 있는 만큼, 국제 협력과 기술 교류를 확대하여 우리나라가 국제 AI 시장에서 주도적인 역할을 할 수 있도록 지원하겠습니다 또한, 글로벌 AI 거버넌스 구축에 기여하고, 주요국과의 협력을 통해 우리 기업이 해외 시장에서도 경쟁력을 갖출 수 있도록 정책적 지원을 아끼지 않겠습니다 넷째, AI 강국으로 가기 위한 지원을 아끼지 않겠습니다 AI 산업의 발전과 글로벌 경쟁에서 뒤처지지 않기 위해선 지금이 골든타임입니다 AI 기본법의 취지에 맞춰 필요한 추가 예산이 적기에 투입될 수 있도록 하겠습니다 이를 위해 추경 편성을 포함한 모든 후속 조치를 신속히 추진하여, 대한민국이 AI 강국으로 도약할 수 있도록 적극 뒷받침하겠습니다 앞으로 국회 과방위는 AI 산업의 성장 기반을 조성하고, 대한민국이 AI 선도국으로 도약할 수 있도록 필요한 모든 정책적 노력을 기울이겠습니다.",
        "embedding": [
          0.0002559569838922471,
          -0.022070463746786118,
          0.011457632295787334,
          -0.029990484938025475,
          -0.02463127113878727,
          0.010936231352388859,
          -0.02317926660180092,
          -0.002027855720371008,
          -0.017120448872447014,
          0.0005284140352159739,
          -0.004263611976057291,
          0.0025228571612387896,
          0.004725613631308079,
          -0.016790447756648064,
          -0.017094049602746964,
          0.01143783237785101,
          0.014797242358326912,
          -0.008164223283529282,
          0.008817625232040882,
          -0.00607201736420393,
          0.013899639248847961,
          -0.0003434072423260659,
          0.00298815849237144,
          0.005375715438276529,
          -0.0023232067469507456,
          0.017212849110364914,
          0.02525167167186737,
          -0.03812170773744583,
          0.0015031542861834168,
          0.017569249495863914,
          0.018242452293634415,
          0.0017160049173980951,
          0.0004331262316554785,
          0.0038478109054267406,
          0.003999611362814903,
          0.010744830593466759,
          0.019483255222439766,
          8.07471078587696e-05,
          0.03503290191292763,
          -0.02534407190978527,
          0.014018439687788486,
          0.010824031196534634,
          0.005240414757281542,
          -0.015800444409251213,
          -0.015140443108975887,
          0.02571367286145687,
          0.010487429797649384,
          -0.00611491734161973,
          -0.010408230125904083,
          0.02436726912856102,
          -0.0055869161151349545,
          0.028459280729293823,
          -0.02321886643767357,
          -0.010593030601739883,
          -0.03471609950065613,
          -0.007590021472424269,
          -0.029937686398625374,
          0.022347664460539818,
          0.0004168324521742761,
          -0.015510044060647488,
          0.009332426823675632,
          -0.0025245072320103645,
          -0.010296029038727283,
          0.01321983803063631,
          -0.014704842120409012,
          0.0011748033575713634,
          -0.014612441882491112,
          0.019879257306456566,
          -0.012579635716974735,
          0.000496238935738802,
          0.03767290711402893,
          0.043243322521448135,
          0.003659710520878434,
          0.0017209548968821764,
          0.022242063656449318,
          -0.008527223952114582,
          0.016051245853304863,
          -0.004900514148175716,
          -0.03292089328169823,
          0.010619429871439934,
          0.0008138648117892444,
          -0.005078714340925217,
          0.008316024206578732,
          -0.014216440729796886,
          0.005052314605563879,
          0.009266426786780357,
          -0.030808888375759125,
          0.018664853647351265,
          0.007253420539200306,
          -0.02321886643767357,
          0.02445966936647892,
          0.0008769775158725679,
          -0.007101620081812143,
          0.028063280507922173,
          -0.030360085889697075,
          0.02320566587150097,
          0.008632824756205082,
          0.017529649659991264,
          -0.013516838662326336,
          -0.02374686859548092,
          0.0005449140444397926,
          -0.019338054582476616,
          -0.04540812969207764,
          -0.010804231278598309,
          -0.026730075478553772,
          -0.010071628727018833,
          0.0020460058003664017,
          -0.004643113352358341,
          0.02667727693915367,
          -0.013741238974034786,
          0.0061050173826515675,
          0.018361251801252365,
          -0.018229251727461815,
          -0.028908083215355873,
          0.0023133065551519394,
          -0.004785013850778341,
          -0.007840822450816631,
          -0.008375423960387707,
          0.005761816632002592,
          0.007590021472424269,
          0.014150440692901611,
          0.03321129456162453,
          0.018506452441215515,
          -0.0006699018995277584,
          0.019932057708501816,
          0.002691157627850771,
          -0.011510432697832584,
          -0.03685450553894043,
          -0.01224303524941206,
          -0.02581927366554737,
          0.042372122406959534,
          -0.007062020245939493,
          0.030703287571668625,
          0.02490847185254097,
          -0.013912839815020561,
          -0.017912451177835464,
          -0.013978839851915836,
          -0.017278850078582764,
          -0.009992428123950958,
          -0.03307929262518883,
          0.02510647103190422,
          0.010401629842817783,
          -0.006567018572241068,
          -0.03851770982146263,
          0.0009528777445666492,
          0.029383283108472824,
          0.027244877070188522,
          0.017173249274492264,
          0.019021254032850266,
          0.02278326451778412,
          -0.006976219825446606,
          -0.018704453483223915,
          -0.015734445303678513,
          0.0033610595855861902,
          0.016645247116684914,
          -0.001052703009918332,
          0.003220809157937765,
          0.013767639175057411,
          -0.0007532271556556225,
          0.011213432066142559,
          -0.0029799086041748524,
          -0.007128020282834768,
          -0.017622049897909164,
          0.0048972140066325665,
          0.0042537120170891285,
          0.020499657839536667,
          -0.009523827582597733,
          0.011193632148206234,
          -0.009523827582597733,
          -0.021568860858678818,
          0.0032785593066364527,
          0.017833251506090164,
          -0.019338054582476616,
          -0.006870619487017393,
          -0.008217023685574532,
          0.007867222651839256,
          0.027878480032086372,
          -0.0057024164125323296,
          -0.02440686896443367,
          0.01209123432636261,
          -0.0038709109649062157,
          -0.014269241131842136,
          0.01261923648416996,
          0.027561679482460022,
          0.010051828809082508,
          0.016790447756648064,
          0.014929242432117462,
          0.007999222725629807,
          0.010018828324973583,
          -0.016262445598840714,
          0.028564881533384323,
          0.017358049750328064,
          0.01145103294402361,
          -0.004115111660212278,
          -0.6124817728996277,
          -0.020961659029126167,
          0.02589847333729267,
          -0.009411626495420933,
          0.008071823045611382,
          0.00019284429436083883,
          0.000809327291790396,
          0.009094825945794582,
          -0.008012423291802406,
          0.029013682156801224,
          -0.03458409756422043,
          0.0049698143266141415,
          -0.02574007399380207,
          -0.012764436192810535,
          -0.017608851194381714,
          -0.018466852605342865,
          0.002504707081243396,
          -0.029700085520744324,
          0.011061631143093109,
          0.02303406596183777,
          -0.022162863984704018,
          0.0008646024507470429,
          -0.006385518237948418,
          -0.00634921807795763,
          0.005118314642459154,
          0.012249634601175785,
          0.010949430987238884,
          0.005751916207373142,
          -0.019483255222439766,
          0.008316024206578732,
          -0.018018051981925964,
          0.01275123655796051,
          0.007147820200771093,
          -0.001461904146708548,
          0.04976414144039154,
          0.014995242469012737,
          -0.011754633858799934,
          0.013054837472736835,
          0.011404832825064659,
          0.028010480105876923,
          -0.014572842046618462,
          -0.029145684093236923,
          0.019839657470583916,
          -0.016407646238803864,
          -0.004649713169783354,
          0.021780062466859818,
          0.018796853721141815,
          -0.010355429723858833,
          -0.0010675530647858977,
          -0.031495291739702225,
          -0.021463261917233467,
          -0.003354459535330534,
          7.383771298918873e-05,
          0.006388818379491568,
          -0.0037818108685314655,
          0.003044258803129196,
          -0.0013835289282724261,
          -0.019153254106640816,
          0.006883819587528706,
          0.011332232505083084,
          0.021397260949015617,
          -0.005346015095710754,
          -0.012817236594855785,
          -0.04672813415527344,
          -0.02328486740589142,
          0.032208092510700226,
          -0.02317926660180092,
          0.010078229010105133,
          -0.03484809771180153,
          0.0029518583323806524,
          -0.006359118036925793,
          0.016460446640849113,
          0.0014907792210578918,
          -0.014784041792154312,
          0.008217023685574532,
          0.02509327232837677,
          0.04672813415527344,
          0.00038156358641572297,
          -0.015246043913066387,
          0.007741821929812431,
          -0.006108317524194717,
          -0.01199883408844471,
          0.014256040565669537,
          0.0019123554229736328,
          0.002583907451480627,
          -0.004715713672339916,
          -0.010718430392444134,
          -0.026782875880599022,
          -0.014440841041505337,
          -0.015259243547916412,
          0.02361486665904522,
          0.018638452515006065,
          0.0027654077857732773,
          -0.028591280803084373,
          0.011424632743000984,
          0.02493487112224102,
          -0.006573618855327368,
          -0.013411237858235836,
          0.0014305540826171637,
          -0.008256623521447182,
          -0.009523827582597733,
          -0.0068376194685697556,
          -0.004567212890833616,
          0.010520430281758308,
          0.015932446345686913,
          0.013820439577102661,
          -0.044404927641153336,
          -0.031548090279102325,
          0.03556090220808983,
          -0.02378646843135357,
          -0.0010485779494047165,
          0.0034089097753167152,
          -0.0036861104890704155,
          0.018823252990841866,
          -0.006408618297427893,
          -0.015378043986856937,
          -0.008071823045611382,
          0.010296029038727283,
          -0.005095214582979679,
          0.007378821261227131,
          0.021621661260724068,
          -0.017344849184155464,
          0.009537027217447758,
          -0.004055711440742016,
          -0.003745510708540678,
          0.0026647576596587896,
          -0.003745510708540678,
          -0.020407257601618767,
          -0.03387129679322243,
          0.006949819624423981,
          -0.029647285118699074,
          -0.02391846850514412,
          0.013569639064371586,
          -0.006421818397939205,
          0.03637930378317833,
          -0.018229251727461815,
          0.017767250537872314,
          -0.018044451251626015,
          -0.005223914980888367,
          -0.01190643385052681,
          -0.006748519372195005,
          0.0061281174421310425,
          0.016882847994565964,
          0.0019206054275855422,
          -0.019945256412029266,
          -0.016368046402931213,
          -0.030201686546206474,
          0.01237503532320261,
          -0.004616713151335716,
          -0.0021285060793161392,
          -0.011972433887422085,
          0.031336888670921326,
          -0.003837910946458578,
          0.019826456904411316,
          0.014295640401542187,
          0.005349315237253904,
          -0.013714838773012161,
          -0.005022614262998104,
          -0.020288458094000816,
          -0.02236086316406727,
          0.0038214109372347593,
          0.001965155592188239,
          -0.013622438535094261,
          -0.030914489179849625,
          0.008566824719309807,
          -0.03461049869656563,
          -0.0019981556106358767,
          0.012216635048389435,
          -0.0023463068064302206,
          -0.03571930155158043,
          0.009675627574324608,
          -0.008263223804533482,
          -0.0021895563695579767,
          0.018783653154969215,
          0.02273046411573887,
          -0.0014297290472313762,
          -0.0004842763883061707,
          0.015470444224774837,
          0.007266620639711618,
          0.004088711459189653,
          -0.008388623595237732,
          -0.0073392209596931934,
          -0.009108025580644608,
          -0.016962047666311264,
          0.03505929931998253,
          0.0029601084534078836,
          0.010665630921721458,
          -0.00016757860430516303,
          -0.010104629211127758,
          0.003983111586421728,
          -0.009596426971256733,
          0.02614927478134632,
          0.013978839851915836,
          0.010513829998672009,
          0.000530063989572227,
          0.005758516490459442,
          -0.00616111746057868,
          0.0075042215175926685,
          0.020948460325598717,
          0.02442006953060627,
          0.03666970506310463,
          0.020103657618165016,
          0.02556847222149372,
          -0.015180042944848537,
          0.013094437308609486,
          -0.003354459535330534,
          -0.0015336794313043356,
          -0.02298126555979252,
          0.013794039376080036,
          -0.006388818379491568,
          0.01271163672208786,
          -0.0066957189701497555,
          -0.006956419907510281,
          -0.010190429165959358,
          -0.005362515337765217,
          0.02313966676592827,
          -0.010104629211127758,
          -0.013807239010930061,
          -0.03764650598168373,
          0.033052895218133926,
          -0.003564010141417384,
          0.012916237115859985,
          0.004062311723828316,
          -0.017859650775790215,
          0.008982625789940357,
          0.012031834572553635,
          0.00040383863961324096,
          0.019839657470583916,
          0.019588856026530266,
          -0.02298126555979252,
          -0.021159660071134567,
          -0.003177909180521965,
          -0.014269241131842136,
          0.016156846657395363,
          0.027799278497695923,
          0.00010451748676132411,
          0.02643967606127262,
          -0.006550518795847893,
          0.028987282887101173,
          -0.005108414683490992,
          -0.012817236594855785,
          0.013094437308609486,
          0.013417838141322136,
          -0.02612287551164627,
          0.02513287216424942,
          -0.011074831709265709,
          0.03645850345492363,
          0.019826456904411316,
          -0.02269086427986622,
          0.005478015635162592,
          -0.02327166683971882,
          0.0037521107587963343,
          0.0015056292759254575,
          -0.005454915575683117,
          0.002717557828873396,
          -0.02719207853078842,
          0.0035013100132346153,
          0.015391243621706963,
          0.01158963330090046,
          0.027429677546024323,
          0.018466852605342865,
          0.02463127113878727,
          0.013490438461303711,
          -0.00033660096232779324,
          -0.0033363094553351402,
          -0.007807822432368994,
          0.012157234363257885,
          0.0010931281140074134,
          -0.014058040454983711,
          -0.019918857142329216,
          -0.00010539405047893524,
          -0.014599241316318512,
          0.012269435450434685,
          -0.02690167725086212,
          0.008151023648679256,
          0.006976219825446606,
          0.0055110156536102295,
          -0.0007891147397458553,
          0.018968453630805016,
          0.021898861974477768,
          0.0034782099537551403,
          -0.03255129233002663,
          -0.0013447538949549198,
          0.017648451030254364,
          0.005408715456724167,
          -0.021529261022806168,
          -0.02432766929268837,
          0.004095311742275953,
          -0.027904879301786423,
          0.019272055476903915,
          -0.02494807168841362,
          0.027614478021860123,
          -0.006279917899519205,
          0.014322040602564812,
          -0.03917771205306053,
          -0.027376879006624222,
          0.0050886147655546665,
          -0.004296612460166216,
          -0.0,
          -0.017727650701999664,
          0.0018364551942795515,
          0.0006043142057023942,
          -0.010566630400717258,
          -0.02568727359175682,
          0.02486887015402317,
          -0.017278850078582764,
          -0.016328446567058563,
          0.005870716646313667,
          -0.003014558693394065,
          -0.03645850345492363,
          -0.02548927254974842,
          -0.016869647428393364,
          0.004633213393390179,
          0.001337328809313476,
          -0.013622438535094261,
          0.008797825314104557,
          -0.015193243511021137,
          -0.016130445525050163,
          0.01274463627487421,
          0.003672910388559103,
          -0.0009495777194388211,
          -0.02315286546945572,
          -0.0038676110561937094,
          0.01191963441669941,
          0.09039385616779327,
          -0.020526058971881866,
          -0.002676307689398527,
          0.0034683099947869778,
          -0.030861688777804375,
          0.009088225662708282,
          -0.007906822487711906,
          -0.043111324310302734,
          0.007794622331857681,
          0.013688439503312111,
          -0.019351255148649216,
          0.015087642706930637,
          0.02298126555979252,
          -0.011041831225156784,
          0.02480287104845047,
          0.03484809771180153,
          0.011272831819951534,
          -0.017305249348282814,
          0.0009594777366146445,
          0.011411432176828384,
          -0.008586624637246132,
          -0.015219643712043762,
          -0.0036168103106319904,
          0.029568083584308624,
          0.013926039449870586,
          -0.005966417025774717,
          0.027772879227995872,
          0.031680092215538025,
          -0.010916431434452534,
          -0.019826456904411316,
          0.004633213393390179,
          -0.0053922152146697044,
          -0.009695427492260933,
          0.01194603368639946,
          0.004108511842787266,
          0.032313693314790726,
          0.0014074540231376886,
          0.02486887015402317,
          -0.017793651670217514,
          -3.619697963586077e-05,
          0.029040083289146423,
          0.030650487169623375,
          0.0019569057039916515,
          -0.018519653007388115,
          -0.005999417044222355,
          -0.016381246969103813,
          0.017384449020028114,
          0.006375618278980255,
          -0.01264563575387001,
          -0.018612053245306015,
          0.020394058898091316,
          -0.018004851415753365,
          -0.043401725590229034,
          0.0012969037052243948,
          0.022677665576338768,
          0.007326020859181881,
          -0.0061017172411084175,
          -0.008118023164570332,
          0.018361251801252365,
          -0.01289643719792366,
          -0.0030162085313349962,
          -0.04622653126716614,
          0.0036432105116546154,
          -0.0008860525558702648,
          -0.02489527128636837,
          -0.010282829403877258,
          -0.018810054287314415,
          0.020130056887865067,
          0.0031020089518278837,
          0.014256040565669537,
          0.014348440803587437,
          -0.020499657839536667,
          -0.02304726652801037,
          -0.029700085520744324,
          0.01158303301781416,
          0.0010081528453156352,
          0.02502727136015892,
          0.004481412936002016,
          -0.016236046329140663,
          0.005237115081399679,
          -0.0005610015941783786,
          -0.00601921696215868,
          -0.02350926771759987,
          -0.008170823566615582,
          0.00038300734013319016,
          0.022308064624667168,
          -0.022308064624667168,
          -0.016896048560738564,
          -0.02226846292614937,
          -0.0004731388471554965,
          0.014150440692901611,
          -0.002826458076015115,
          0.030360085889697075,
          0.011332232505083084,
          -0.004745413549244404,
          -0.009167426265776157,
          0.010784430429339409,
          -0.017001649364829063,
          -0.01139163225889206,
          -0.01288983691483736,
          0.016618847846984863,
          -0.02337726764380932,
          -0.014889642596244812,
          0.017569249495863914,
          -0.013675238937139511,
          0.014784041792154312,
          0.014427641406655312,
          0.009094825945794582,
          0.010296029038727283,
          0.022057263180613518,
          0.006666019093245268,
          -0.014850042760372162,
          0.015826845541596413,
          -0.04712413623929024,
          -0.013886439613997936,
          -0.014018439687788486,
          0.0001401472691213712,
          -0.01293603703379631,
          0.0009768027812242508,
          0.009853827767074108,
          -0.014190040528774261,
          -0.031125688925385475,
          0.021463261917233467,
          0.013886439613997936,
          -0.017806850373744965,
          0.03450489789247513,
          -0.0028512082062661648,
          0.0006319517851807177,
          -0.016354845836758614,
          -0.009471027180552483,
          0.004517713095992804,
          0.005600116215646267,
          0.010104629211127758,
          0.010045228525996208,
          0.018136851489543915,
          -0.004408812616020441,
          -0.007114820182323456,
          0.012586236000061035,
          -0.01144443266093731,
          -0.02633407525718212,
          -0.006956419907510281,
          -0.017107248306274414,
          0.004006211645901203,
          -0.01205163449048996,
          0.005385615397244692,
          -0.032973695546388626,
          -0.007669222075492144,
          0.013569639064371586,
          -0.0038280109874904156,
          0.022387264296412468,
          -0.03608890250325203,
          0.005372415296733379,
          -0.01153023261576891,
          0.005296515300869942,
          -0.0006674269097857177,
          -0.02291526459157467,
          -0.001961855683475733,
          -0.019206054508686066,
          0.05066174641251564,
          0.014506841078400612,
          0.02642647549510002,
          -0.006778219249099493,
          0.016024846583604813,
          0.02395806834101677,
          0.009101426228880882,
          -0.014916042797267437,
          0.005550615955144167,
          -0.0007858147728256881,
          -0.009372026659548283,
          0.010890031233429909,
          0.00653401855379343,
          0.03664330393075943,
          0.017476849257946014,
          -0.0009132776176556945,
          -0.0023842568043619394,
          0.017740851268172264,
          -0.0044715129770338535,
          -0.017688050866127014,
          -0.014625641517341137,
          -0.028142480179667473,
          -0.015048042871057987,
          -0.0042537120170891285,
          0.010645830072462559,
          -0.004125011619180441,
          -0.02670367620885372,
          0.001451179152354598,
          0.02299446612596512,
          0.020235657691955566,
          0.030650487169623375,
          0.004092011600732803,
          0.02290206588804722,
          -0.02576647326350212,
          0.017344849184155464,
          0.031680092215538025,
          -0.0060786171816289425,
          -0.0019552556332200766,
          -0.008335824124515057,
          -0.019351255148649216,
          0.009339027106761932,
          0.014995242469012737,
          0.02599087357521057,
          -0.0024717070627957582,
          0.0062205176800489426,
          -0.007451421115547419,
          -0.012177035212516785,
          0.007807822432368994,
          -0.031389690935611725,
          -0.015628844499588013,
          0.006015917286276817,
          -0.03387129679322243,
          -0.020763659849762917,
          -0.031046489253640175,
          -0.007220420520752668,
          -0.04004891589283943,
          0.013153837993741035,
          -0.012586236000061035,
          -0.005428515374660492,
          0.015246043913066387,
          0.01255323551595211,
          -0.02378646843135357,
          0.02436726912856102,
          0.01209123432636261,
          0.02299446612596512,
          -0.015430844388902187,
          0.030703287571668625,
          0.02341686747968197,
          -0.0016673298086971045,
          -0.021582061424851418,
          0.008368823677301407,
          -0.016764048486948013,
          -0.000969377753790468,
          0.02328486740589142,
          -0.004224012140184641,
          -0.03954731300473213,
          -0.0055110156536102295,
          0.02291526459157467,
          0.014533241279423237,
          -0.016236046329140663,
          -0.03505929931998253,
          0.02481607161462307,
          0.008850625716149807,
          0.018981654196977615,
          0.008322623558342457,
          -0.02541007287800312,
          0.0020262058824300766,
          0.029330484569072723,
          0.0012729786103591323,
          -0.016896048560738564,
          -0.02719207853078842,
          -0.027165677398443222,
          0.011550032533705235,
          0.0013917789328843355,
          -0.020829658955335617,
          0.027482477948069572,
          0.01339803822338581,
          -0.016671648249030113,
          -0.010645830072462559,
          -0.013820439577102661,
          -0.004527613054960966,
          0.021225661039352417,
          -0.021582061424851418,
          0.028644081205129623,
          -0.022954866290092468,
          0.021291660144925117,
          -0.018453652039170265,
          -0.01129923202097416,
          -0.005451615434139967,
          -0.016566047444939613,
          -0.008401824161410332,
          0.042055319994688034,
          -0.017925651744008064,
          -0.000844802416395396,
          0.006550518795847893,
          -0.005481315776705742,
          0.04018091410398483,
          -0.018625253811478615,
          0.002034455770626664,
          -0.00012148160021752119,
          -0.029304083436727524,
          0.007471221499145031,
          0.017912451177835464,
          0.013609238900244236,
          -0.0054615153931081295,
          0.001326603814959526,
          -0.005362515337765217,
          -0.018242452293634415,
          0.003544210223481059,
          0.003834611037746072,
          0.015747645869851112,
          0.07291700690984726,
          0.0074118212796747684,
          0.021291660144925117,
          -0.017001649364829063,
          -0.002605357440188527,
          0.021093660965561867,
          -0.01265223603695631,
          -0.0074580213986337185,
          0.016315246000885963,
          -0.008250023238360882,
          -0.0025905075017362833,
          0.010091428644955158,
          0.012342034839093685,
          0.009226826019585133,
          -0.009708628058433533,
          0.0007445646333508193,
          -0.019998056814074516,
          0.030254486948251724,
          -0.015008443035185337,
          -0.015958845615386963,
          -0.013754439540207386,
          -0.0017011548625305295,
          0.01321983803063631,
          -0.015048042871057987,
          0.014572842046618462,
          0.00315150897949934,
          -0.0074844215996563435,
          -0.007253420539200306,
          0.007029020227491856,
          -0.011279432103037834,
          0.016698047518730164,
          0.007180820684880018,
          0.00148335425183177,
          0.019496455788612366,
          -0.02283606491982937,
          -0.019113654270768166,
          -0.00578821636736393,
          0.02353566698729992,
          -0.0024997571017593145,
          -0.05169134587049484,
          -0.010236629284918308,
          0.015853244811296463,
          0.019034454599022865,
          -0.012302435003221035,
          -0.0013406288344413042,
          -0.004722313489764929,
          -0.012546636164188385,
          -0.02593807317316532,
          -0.011220032349228859,
          0.001072503044269979,
          -0.007722022011876106,
          0.010243229568004608,
          0.007128020282834768,
          0.008058623410761356,
          0.008052023127675056,
          -0.0003887823550030589,
          -0.005751916207373142,
          -0.003930311184376478,
          -0.02356206811964512,
          -0.03424089774489403,
          0.018757253885269165,
          -0.012823836877942085,
          0.04807453602552414,
          -0.005006114486604929,
          -0.014084440656006336,
          -0.020803259685635567,
          0.01325943786650896,
          -0.04012811556458473,
          -0.015694845467805862,
          0.028670482337474823,
          0.0038181107956916094,
          -0.008646024391055107,
          0.015628844499588013,
          0.02430127002298832,
          0.022809665650129318,
          -0.0017061048420146108,
          0.018506452441215515,
          -0.0014627291820943356,
          -0.028512081131339073,
          0.02471047081053257,
          -0.013384838588535786,
          0.005412015598267317,
          0.007332621142268181,
          -0.014850042760372162,
          0.005966417025774717,
          0.011074831709265709,
          0.010771230794489384,
          -0.010777831077575684,
          0.04060331732034683,
          0.006669319234788418,
          -0.022862466052174568,
          0.02300766482949257,
          0.01241463515907526,
          -0.03732970729470253,
          0.011338832788169384,
          0.014388040639460087,
          -0.019826456904411316,
          0.014031640253961086,
          0.004669513553380966,
          -0.013965640217065811,
          -0.02451246976852417,
          0.02336406707763672,
          0.0008130398346111178,
          0.0026845575775951147,
          0.009708628058433533,
          0.014190040528774261,
          -0.0020179557614028454,
          0.0009512277320027351,
          -0.007392020896077156,
          0.03323769569396973,
          0.021436860784888268,
          0.013873239979147911,
          0.004309812095016241,
          0.008758225478231907,
          -0.018546052277088165,
          -0.015747645869851112,
          -0.0010865280637517571,
          -0.015800444409251213,
          0.0011715033324435353,
          0.016513247042894363,
          -0.0022720564156770706,
          0.018136851489543915,
          -0.002374356845393777,
          0.011226631700992584,
          -0.031521689146757126,
          0.003649810329079628,
          0.017754049971699715,
          0.008375423960387707,
          -0.044985730201005936,
          0.030386487022042274,
          0.015325243584811687,
          -0.028459280729293823,
          -0.0061512175016105175,
          -0.0074118212796747684,
          -0.01238163560628891,
          -0.03864971175789833,
          -0.02255886420607567,
          0.002697757678106427,
          -0.032472092658281326,
          0.007260020822286606,
          0.030861688777804375,
          -0.02465767040848732,
          -0.005709016229957342,
          -0.008078423328697681,
          0.007134620565921068,
          -0.019034454599022865,
          -0.004336212296038866,
          0.2610439360141754,
          -0.028089679777622223,
          -0.007200620602816343,
          0.007444821298122406,
          -0.016935648396611214,
          0.006408618297427893,
          0.018466852605342865,
          -0.005784916691482067,
          -0.0037092105485498905,
          -0.0006092642433941364,
          -0.04643773287534714,
          0.017120448872447014,
          -0.010876830667257309,
          -0.016328446567058563,
          0.009438026696443558,
          -0.03255129233002663,
          -0.044484127312898636,
          -0.029330484569072723,
          -0.005989517085254192,
          0.017622049897909164,
          0.0025179071817547083,
          -0.0033478594850748777,
          -0.016632048413157463,
          -0.003920411225408316,
          0.004356012213975191,
          -7.363146141869947e-05,
          -0.007801222149282694,
          0.004121711943298578,
          -0.0018892553634941578,
          0.011477433145046234,
          -0.026888476684689522,
          -0.0016211295733228326,
          0.015906045213341713,
          -0.008560224436223507,
          -0.019918857142329216,
          -0.020961659029126167,
          0.028380081057548523,
          -0.0017259048763662577,
          0.013061437755823135,
          0.01178103405982256,
          -0.007035620044916868,
          0.012454235926270485,
          0.003993011545389891,
          -0.01201203465461731,
          0.02713927812874317,
          0.031680092215538025,
          -0.002234106417745352,
          -0.008758225478231907,
          -0.030993688851594925,
          0.001968455733731389,
          -0.022664465010166168,
          -0.032023292034864426,
          0.008936425670981407,
          0.04575132951140404,
          0.008019022643566132,
          0.010117828845977783,
          -0.012031834572553635,
          0.0034221098758280277,
          -0.0002730757696554065,
          0.030016886070370674,
          -0.013140637427568436,
          0.031732890754938126,
          -0.014797242358326912,
          0.032023292034864426,
          -0.028274480253458023,
          -0.002253906335681677,
          -0.016434047371149063,
          0.032973695546388626,
          0.02327166683971882,
          -0.013510238379240036,
          -0.010309229604899883,
          -0.013833639211952686,
          -0.021753661334514618,
          -0.01205163449048996,
          -0.030518487095832825,
          -0.031178489327430725,
          0.04593612998723984,
          0.03857050836086273,
          0.007095020264387131,
          0.004903813824057579,
          -0.008982625789940357,
          -0.006286518182605505,
          0.02435407042503357,
          0.009160825982689857,
          -0.016104046255350113,
          -0.0031086087692528963,
          -0.009840628132224083,
          0.0048477137461304665,
          -0.008441423997282982,
          -0.006382218096405268,
          -0.0014256041031330824,
          0.010447829961776733,
          -0.015668444335460663,
          -0.02636047452688217,
          -0.005705716088414192,
          -0.019417256116867065,
          0.011503832414746284,
          -0.008738424628973007,
          -0.020565658807754517,
          0.008910025469958782,
          -0.013648838736116886,
          0.03933611139655113,
          0.0035310101229697466,
          0.021001260727643967,
          0.009715227410197258,
          0.011424632743000984,
          0.003465009853243828,
          0.014770842157304287,
          0.009814227931201458,
          -0.020842859521508217,
          -0.005725516472011805,
          -0.015298843383789062,
          0.017160048708319664,
          0.005355915520340204,
          -0.007596621755510569,
          0.009708628058433533,
          0.002004755660891533,
          -0.026545275002717972,
          0.02628127485513687,
          -0.017714450135827065,
          -0.020710859447717667,
          -0.021397260949015617,
          -0.02456527017056942,
          0.005478015635162592,
          -0.0025905075017362833,
          -0.01237503532320261,
          -0.009873628616333008,
          0.01345083862543106,
          -0.0020014557521790266,
          -0.02526487223803997,
          -0.0021169560495764017,
          -0.028380081057548523,
          0.026782875880599022,
          0.0042801122181117535,
          0.0014767542015761137,
          -0.00667591905221343,
          -0.001435504062101245,
          0.01139163225889206,
          0.005491215735673904,
          -0.004243812058120966,
          -0.00036506354808807373,
          0.001321653719060123,
          0.010586430318653584,
          0.00038568858872167766,
          -0.005286614876240492,
          0.0002567819901742041,
          0.016447246074676514,
          0.006243617739528418,
          0.004101911559700966,
          0.00593671714887023,
          -0.013424438424408436,
          0.020882459357380867,
          -0.008243423886597157,
          -0.018295252695679665,
          0.02461807057261467,
          0.014044839888811111,
          -0.017793651670217514,
          -0.007741821929812431,
          0.0029980584513396025,
          0.03777850791811943,
          -0.057129763066768646,
          0.001623604679480195,
          0.05018654465675354,
          -0.04873453825712204,
          -0.03336969390511513,
          -0.010322429239749908,
          -0.16642607748508453,
          0.02478967048227787,
          0.03991691395640373,
          -0.01171503309160471,
          0.022770065814256668,
          0.018942054361104965,
          0.014546441845595837,
          0.0013719788985326886,
          0.004540813155472279,
          -0.017833251506090164,
          0.020235657691955566,
          0.0037356107495725155,
          -0.010632630437612534,
          0.0074052209965884686,
          0.027244877070188522,
          0.009240026585757732,
          -0.05092574656009674,
          0.020116858184337616,
          0.0021829563193023205,
          0.0034518097527325153,
          -0.0036465104203671217,
          -0.026888476684689522,
          -0.002468407154083252,
          -0.00038073858013376594,
          0.016130445525050163,
          -0.0018645053496584296,
          -0.019456855952739716,
          -0.012256234884262085,
          -0.008349023759365082,
          -0.018968453630805016,
          -0.0015534794656559825,
          -0.02592487446963787,
          0.027020476758480072,
          -0.01144443266093731,
          0.031891290098428726,
          0.00016500047058798373,
          -0.007372220978140831,
          -0.0038511110469698906,
          -0.03651130571961403,
          0.030122486874461174,
          0.004719013348221779,
          0.030808888375759125,
          0.02492167055606842,
          0.0033693097066134214,
          -0.027244877070188522,
          0.005814616568386555,
          -0.005596816074103117,
          -0.008646024391055107,
          0.015985244885087013,
          -0.0016945548122748733,
          -0.004679413512349129,
          -0.03421449661254883,
          0.005299814976751804,
          0.010276229120790958,
          0.012256234884262085,
          0.03685450553894043,
          0.013464038260281086,
          -0.02311326563358307,
          -0.0067716194316744804,
          0.010289429686963558,
          -0.009372026659548283,
          0.004042511340230703,
          0.02344326674938202,
          -0.022809665650129318,
          -0.0015889545902609825,
          0.004732213448733091,
          -0.010164028964936733,
          0.019113654270768166,
          -0.03215529024600983,
          -0.0015683295205235481,
          -0.0031878091394901276,
          0.022228863090276718,
          -0.0003927011275663972,
          -0.009556827135384083,
          0.007128020282834768,
          -0.02522527240216732,
          -0.009649227373301983,
          0.011708433739840984,
          0.0008464524289593101,
          0.006421818397939205,
          0.0003539260069373995,
          0.0034551098942756653,
          -0.031099289655685425,
          -0.004497912712395191,
          -0.006015917286276817,
          0.018440453335642815,
          0.01359603926539421,
          0.006510918494313955,
          -0.014836842194199562,
          0.006190817803144455,
          0.018110452219843864,
          -0.007768222130835056,
          0.0022984566166996956,
          0.005959817208349705,
          0.02302086539566517,
          0.03611530363559723,
          -0.014071240089833736,
          0.011371832340955734,
          -0.02665087580680847,
          -0.0038973111659288406,
          0.0028611081652343273,
          0.008263223804533482,
          -0.017833251506090164,
          0.019734056666493416,
          -0.0012919537257403135,
          0.031759291887283325,
          0.011074831709265709,
          0.020050857216119766,
          0.04609453305602074,
          -0.014968843199312687,
          -0.0008072648197412491,
          0.006012617144733667,
          0.021476460620760918,
          0.028142480179667473,
          0.0014239540323615074,
          0.04759933426976204,
          -0.042926523834466934,
          -0.014348440803587437,
          -0.005877316929399967,
          0.005946617107838392,
          0.04802173748612404,
          -0.01278423611074686,
          -0.008824225515127182,
          0.0068178195506334305,
          -0.012269435450434685,
          0.0054384153336286545,
          -0.07418420910835266,
          -0.03424089774489403,
          0.01298883743584156,
          0.019166454672813416,
          -0.008566824719309807,
          -0.0028000581078231335,
          -0.00583441648632288,
          0.014797242358326912,
          -0.05850256606936455,
          -0.0033445595763623714,
          -0.043348923325538635,
          -0.04902493953704834,
          -0.005187614820897579,
          -0.007867222651839256,
          0.011134231463074684,
          -0.014559641480445862,
          -0.02667727693915367,
          -0.011979034170508385,
          0.007867222651839256,
          0.014691641554236412,
          -8.956431702245027e-05,
          0.010942831635475159,
          0.018876053392887115,
          -0.03252489119768143,
          -0.020592058077454567,
          -0.0042075118981301785,
          -0.029172083362936974,
          0.028380081057548523,
          0.019720856100320816,
          0.019800055772066116,
          -0.008085022680461407,
          -0.011649033054709435,
          -0.004950013943016529,
          -0.011655633337795734,
          0.0024288068525493145,
          -0.02270406484603882,
          -0.019998056814074516,
          -0.018783653154969215,
          0.016104046255350113,
          -0.002037755912169814,
          0.011886633932590485,
          0.014322040602564812,
          0.021080460399389267,
          -0.019324855878949165,
          -0.006567018572241068,
          -0.017160048708319664,
          -0.007345820777118206,
          0.030914489179849625,
          0.003090458922088146,
          -0.02472367137670517,
          -0.03395049646496773,
          -0.02320566587150097,
          -0.04018091410398483,
          0.00569911627098918,
          0.03395049646496773,
          0.0008827525307424366,
          0.028274480253458023,
          -0.017938850447535515,
          -0.007365621160715818,
          0.005428515374660492,
          -0.016988448798656464,
          0.02481607161462307,
          7.311583613045514e-05,
          -0.02438046969473362,
          0.016288846731185913,
          0.016209647059440613,
          -0.0020872559398412704,
          0.020948460325598717,
          0.013200038112699986,
          0.00602911738678813,
          0.03339609503746033,
          0.002902358304709196,
          -0.02302086539566517,
          0.030544886365532875,
          -0.030940888449549675,
          -0.029647285118699074,
          -0.02411646954715252,
          -0.018136851489543915,
          0.03379209712147713,
          0.002351256785914302,
          -0.021780062466859818,
          -0.013338638469576836,
          0.010659030638635159,
          -0.0004376637516543269,
          0.008065222762525082,
          0.012434435077011585,
          -0.017107248306274414,
          -0.013365037739276886,
          -0.0030294086318463087,
          -0.030729686841368675,
          0.015219643712043762,
          -6.48658096906729e-05,
          0.007425021380186081,
          0.0009644277743063867,
          0.008487624116241932,
          0.007293020840734243,
          -0.007893622852861881,
          0.008467824198305607,
          0.005959817208349705,
          0.013754439540207386,
          -0.027376879006624222,
          -0.028116080909967422,
          -0.07756341993808746,
          0.02562127262353897,
          0.005352615378797054,
          -0.022004462778568268,
          -0.031257688999176025,
          -0.006982820108532906,
          0.02428806945681572,
          -0.019404055550694466,
          -0.00041641993448138237,
          0.007068620063364506,
          -0.007326020859181881,
          0.0062271179631352425,
          -0.008137823082506657,
          0.0017341549973934889,
          -0.018704453483223915,
          -0.02373366802930832,
          0.029515285044908524,
          -0.004389012698084116,
          0.014110839925706387,
          -0.013008637353777885,
          0.018691252917051315,
          0.020143257454037666,
          0.013391437940299511,
          0.01164243370294571,
          -0.029092883691191673,
          -0.0024370569735765457,
          -0.031178489327430725,
          0.005118314642459154,
          0.012447635643184185,
          0.007695621810853481,
          0.008177422918379307,
          -0.021938461810350418,
          -0.022242063656449318,
          -0.00045003878767602146,
          -0.019113654270768166,
          0.0020443557295948267,
          0.008236823603510857,
          0.03756730630993843,
          0.030993688851594925,
          0.044193726032972336,
          -0.020050857216119766,
          -0.028406480327248573,
          0.021027659997344017,
          -0.013516838662326336,
          -0.005689216312021017,
          0.016368046402931213,
          -0.007246820721775293,
          -0.003603610210120678,
          0.02575327269732952,
          -0.009972628206014633,
          -0.0055143157951533794,
          0.02299446612596512,
          -0.028987282887101173,
          -0.018915653228759766,
          -0.0022060563787817955,
          -0.015364843420684338,
          0.04781053587794304,
          0.018942054361104965,
          0.016288846731185913,
          0.008269823156297207,
          0.016038045287132263,
          -0.009134425781667233,
          0.011609433218836784,
          0.00635581836104393,
          0.003316509537398815,
          -0.0055143157951533794,
          -0.02254566363990307,
          -0.010381829924881458,
          0.014203240163624287,
          -0.02349606715142727,
          -0.02581927366554737,
          -0.019087255001068115,
          0.0015468794154003263,
          -0.008929825387895107,
          -0.016552846878767014,
          0.016288846731185913,
          -0.0048708138056099415,
          -0.014216440729796886,
          -0.012447635643184185,
          0.01345083862543106,
          0.006976219825446606,
          -0.010929631069302559,
          -0.010632630437612534,
          -0.006689119152724743,
          0.0012639035703614354,
          0.020724060013890266,
          -0.02558167278766632,
          0.016302047297358513,
          -0.008058623410761356,
          -0.004649713169783354,
          -0.042847324162721634,
          0.02529127150774002,
          0.020314857363700867,
          -0.008382024243474007,
          0.008428224362432957,
          0.010975831188261509,
          0.0061017172411084175,
          0.013622438535094261,
          0.014559641480445862,
          -0.017080849036574364,
          0.015312043949961662,
          -0.013457437977194786,
          0.03331689536571503,
          0.010025428608059883,
          -0.03725050762295723,
          0.0016483546933159232,
          -0.016170045360922813,
          -0.0019536055624485016,
          -0.016909249126911163,
          0.008613024838268757,
          0.009193826466798782,
          0.02546287328004837,
          -0.0015411044005304575,
          0.013226437382400036,
          -0.029224883764982224,
          0.028828881680965424,
          0.009259826503694057,
          -0.016764048486948013,
          -0.04976414144039154,
          0.029488883912563324,
          0.02362806722521782,
          0.021106859669089317,
          0.027878480032086372,
          -0.031310491263866425,
          0.04065611585974693,
          0.03696010634303093,
          0.008256623521447182,
          -0.008573424071073532,
          0.007240220904350281,
          0.008104823529720306,
          -0.004728913307189941,
          0.014216440729796886,
          -0.028485681861639023,
          -0.0025558574125170708,
          -0.019536055624485016,
          0.008487624116241932,
          0.014454041607677937,
          0.00020130057237111032,
          0.00322245922870934,
          0.05235134810209274,
          0.03527050092816353,
          0.014493641443550587,
          0.001264728605747223,
          0.01162263285368681,
          -0.003544210223481059,
          0.019839657470583916,
          -0.006006017327308655,
          -0.013186837546527386,
          -0.010804231278598309,
          0.004540813155472279,
          -0.005253614857792854,
          -0.004293312318623066,
          -0.03967931494116783,
          0.0016211295733228326,
          -0.0020872559398412704,
          -0.004626613110303879,
          0.032788895070552826,
          -0.005738716572523117,
          -0.0028215080965310335,
          0.022624865174293518,
          0.0074316211976110935,
          -0.011200232431292534,
          0.020301658660173416,
          -0.017886051908135414,
          -0.013675238937139511,
          0.010989031754434109,
          -0.02250606380403042,
          0.016816848888993263,
          -0.020473258569836617,
          0.003837910946458578,
          -0.0012144034262746572,
          -0.028723282739520073,
          -0.018176451325416565,
          -0.007807822432368994,
          0.006517518777400255,
          -0.00024007567844819278,
          0.015787245705723763,
          0.00021027246839366853,
          -0.0006996020092628896,
          0.01302183698862791,
          0.013444238342344761,
          -0.018348053097724915,
          -0.004009511321783066,
          0.0013645539293065667,
          0.008111422881484032,
          -0.02290206588804722,
          -0.028934482485055923,
          -0.0009850527858361602
        ]
      }
    ]
  }
}